[{"name": "Alit Hide", "weight": 1.0, "value": 5, "first": "Drain Intelligence", "second": "Resist Poison", "third": "Telekinesis", "fourth": "Detect Animal", "ID": "ingred_alit_hide_01"}, {"name": "Ampoule Pod", "weight": 0.1, "value": 2, "first": "Water Walking", "second": "Paralyze", "third": "Detect Animal", "fourth": "Drain Willpower", "ID": "ingred_bc_ampoule_pod"}, {"name": "Ash Salts", "weight": 0.1, "value": 25, "first": "Drain Agility", "second": "Resist Magicka", "third": "Cure Blight Disease", "fourth": "Resist Magicka", "ID": "ingred_ash_salts_01"}, {"name": "Ash Yam", "weight": 0.5, "value": 1, "first": "Fortify Intelligence", "second": "Fortify Strength", "third": "Resist Common Disease", "fourth": "Detect Key", "ID": "ingred_ash_yam_01"}, {"name": "Bittergreen Petals", "weight": 0.1, "value": 5, "first": "Restore Intelligence", "second": "Invisibility", "third": "Drain Endurance", "fourth": "Drain Magicka", "ID": "ingred_bittergreen_petals_01"}, {"name": "Black Anther", "weight": 0.1, "value": 2, "first": "Drain Agility", "second": "Resist Fire", "third": "Drain Endurance", "fourth": "Light", "ID": "ingred_black_anther_01"}, {"name": "Black Lichen", "weight": 0.1, "value": 2, "first": "Drain Strength", "second": "Resist Frost", "third": "Drain Speed", "fourth": "Cure Poison", "ID": "ingred_black_lichen_01"}, {"name": "Bloat", "weight": 0.1, "value": 5, "first": "Drain Magicka", "second": "Fortify Intelligence", "third": "Fortify Willpower", "fourth": "Detect Animal", "ID": "ingred_bloat_01"}, {"name": "Bonemeal", "weight": 0.2, "value": 2, "first": "Restore Agility", "second": "Telekinesis", "third": "Drain Fatigue", "fourth": "Drain Personality", "ID": "ingred_bonemeal_01"}, {"name": "Bread", "weight": 0.2, "value": 1, "first": "Restore Fatigue", "second": null, "third": null, "fourth": null, "ID": "ingred_bread_01, ingred_bread_01_UNI2"}, {"name": "Bungler's Bane", "weight": 0.5, "value": 1, "first": "Drain Speed", "second": "Drain Endurance", "third": "Dispel", "fourth": "Drain Strength", "ID": "ingred_bc_bungler's_bane"}, {"name": "Chokeweed", "weight": 0.1, "value": 1, "first": "Drain Luck", "second": "Restore Fatigue", "third": "Cure Common Disease", "fourth": "Drain Willpower", "ID": "ingred_chokeweed_01"}, {"name": "Coda Flower", "weight": 0.1, "value": 23, "first": "Drain Personality", "second": "Levitate", "third": "Drain Intelligence", "fourth": "Drain Health", "ID": "ingred_bc_coda_flower"}, {"name": "Comberry", "weight": 0.1, "value": 2, "first": "Drain Fatigue", "second": "Restore Magicka", "third": "Fire Shield", "fourth": "Reflect", "ID": "ingred_comberry_01"}, {"name": "Corkbulb Root", "weight": 0.1, "value": 5, "first": "Cure Paralyzation", "second": "Restore Health", "third": "Lightning Shield", "fourth": "Fortify Luck", "ID": "ingred_corkbulb_root_01"}, {"name": "Corprus Weepings", "weight": 0.1, "value": 50, "first": "Drain Fatigue", "second": "Fortify Luck", "third": "Drain Willpower", "fourth": "Restore Health", "ID": "ingred_corprus_weepings_01"}, {"name": "Crab Meat", "weight": 0.5, "value": 1, "first": "Restore Fatigue", "second": "Resist Shock", "third": "Lightning Shield", "fourth": "Restore Luck", "ID": "ingred_crab_meat_01"}, {"name": "Daedra Skin", "weight": 0.2, "value": 200, "first": "Fortify Strength", "second": "Cure Common Disease", "third": "Paralyze", "fourth": "Swift Swim", "ID": "ingred_daedra_skin_01"}, {"name": "Daedra's Heart", "weight": 1.0, "value": 200, "first": "Restore Magicka", "second": "Fortify Endurance", "third": "Drain Agility", "fourth": null, "ID": "ingred_daedras_heart_01, ingred_cursed_daedras_heart_01"}, {"name": "Diamond", "weight": 0.2, "value": 250, "first": "Drain Agility", "second": "Invisibility", "third": "Reflect", "fourth": "Detect Key", "ID": "ingred_diamond_01, ingred_Dae_cursed_diamond_01"}, {"name": "Dreugh Wax", "weight": 0.2, "value": 100, "first": "Fortify Strength", "second": "Restore Strength", "third": "Drain Luck", "fourth": "Drain Willpower", "ID": "ingred_dreugh_wax_01"}, {"name": "Ectoplasm", "weight": 0.1, "value": 10, "first": "Fortify Agility", "second": "Detect Animal", "third": "Drain Strength", "fourth": "Drain Health", "ID": "ingred_ectoplasm_01"}, {"name": "Emerald", "weight": 0.2, "value": 150, "first": "Fortify Magicka", "second": "Restore Health", "third": "Drain Agility", "fourth": "Drain Endurance", "ID": "ingred_emerald_01, ingred_Dae_cursed_emerald_01"}, {"name": "Fire Petal", "weight": 0.1, "value": 2, "first": "Resist Fire", "second": "Drain Health", "third": "Spell Absorption", "fourth": "Paralyze", "ID": "ingred_fire_petal_01"}, {"name": "Fire Salts", "weight": 0.1, "value": 100, "first": "Drain Health", "second": "Fortify Agility", "third": "Resist Frost", "fourth": "Fire Shield", "ID": "ingred_fire_salts_01"}, {"name": "Frost Salts", "weight": 0.1, "value": 75, "first": "Drain Speed", "second": "Restore Magicka", "third": "Frost Shield", "fourth": "Resist Fire", "ID": "ingred_frost_salts_01"}, {"name": "Ghoul Heart", "weight": 0.5, "value": 150, "first": "Paralyze", "second": "Cure Poison", "third": "Fortify Attack", "fourth": null, "ID": "ingred_ghoul_heart_01"}, {"name": "Girith's Guar Hide", "weight": 1.0, "value": 5, "first": "Drain Fatigue", "second": "Fortify Endurance", "third": "Restore Personality", "fourth": "Fortify Luck", "ID": "ingred_guar_hide_girith"}, {"name": "Gold Kanet", "weight": 0.1, "value": 5, "first": "Drain Health", "second": "Burden", "third": "Drain Luck", "fourth": "Restore Strength", "ID": "ingred_gold_kanet_01"}, {"name": "Gravedust", "weight": 0.1, "value": 1, "first": "Drain Intelligence", "second": "Cure Common Disease", "third": "Drain Magicka", "fourth": "Restore Endurance", "ID": "ingred_gravedust_01"}, {"name": "Green Lichen", "weight": 0.1, "value": 1, "first": "Fortify Personality", "second": "Cure Common Disease", "third": "Drain Strength", "fourth": "Drain Health", "ID": "ingred_green_lichen_01"}, {"name": "Guar Hide", "weight": 1.0, "value": 5, "first": "Drain Fatigue", "second": "Fortify Endurance", "third": "Restore Personality", "fourth": "Fortify Luck", "ID": "ingred_guar_hide_01"}, {"name": "Hackle-Lo Leaf", "weight": 0.1, "value": 30, "first": "Restore Fatigue", "second": "Paralyze", "third": "Water Breathing", "fourth": "Restore Luck", "ID": "ingred_hackle-lo_leaf_01"}, {"name": "Heather", "weight": 0.1, "value": 1, "first": "Restore Personality", "second": "Feather", "third": "Drain Speed", "fourth": "Drain Personality", "ID": "ingred_heather_01"}, {"name": "Hound Meat", "weight": 1.0, "value": 2, "first": "Restore Fatigue", "second": "Fortify Fatigue", "third": "Reflect", "fourth": "Detect Enchantment", "ID": "ingred_hound_meat_01"}, {"name": "Human Flesh", "weight": 1.0, "value": 1, "first": "Fortify Health", "second": "Drain Intelligence", "third": "Drain Personality", "fourth": null, "ID": "ingred_human_meat_01"}, {"name": "Hypha Facia", "weight": 0.1, "value": 1, "first": "Drain Luck", "second": "Drain Agility", "third": "Drain Fatigue", "fourth": "Detect Enchantment", "ID": "ingred_bc_hypha_facia"}, {"name": "Kagouti Hide", "weight": 1.0, "value": 2, "first": "Drain Fatigue", "second": "Fortify Speed", "third": "Resist Common Disease", "fourth": null, "ID": "ingred_kagouti_hide_01"}, {"name": "Kresh Fiber", "weight": 0.1, "value": 1, "first": "Restore Luck", "second": "Fortify Personality", "third": "Drain Magicka", "fourth": "Drain Speed", "ID": "ingred_kresh_fiber_01"}, {"name": "Kwama Cuttle", "weight": 0.1, "value": 2, "first": "Resist Poison", "second": "Drain Fatigue", "third": "Water Walking", "fourth": "Water Breathing", "ID": "ingred_kwama_cuttle_01"}, {"name": "Large Corprusmeat Hunk", "weight": 1.0, "value": 0, "first": "Drain Fatigue", "second": "Drain Health", "third": "Drain Magicka", "fourth": null, "ID": "ingred_6th_corprusmeat_05"}, {"name": "Large Kwama Egg", "weight": 2.0, "value": 2, "first": "Restore Fatigue", "second": "Paralyze", "third": "Frost Shield", "fourth": "Fortify Health", "ID": "food_kwama_egg_02"}, {"name": "Large Wrapped Corprusmeat", "weight": 1.0, "value": 0, "first": "Drain Fatigue", "second": "Drain Health", "third": "Drain Magicka", "fourth": null, "ID": "ingred_6th_corprusmeat_01"}, {"name": "Luminous Russula", "weight": 0.2, "value": 1, "first": "Water Breathing", "second": "Drain Fatigue", "third": "Poison", "fourth": null, "ID": "ingred_russula_01"}, {"name": "Marshmerrow", "weight": 0.1, "value": 1, "first": "Restore Health", "second": "Detect Enchantment", "third": "Drain Willpower", "fourth": "Drain Fatigue", "ID": "ingred_marshmerrow_01"}, {"name": "Marsus' Guar Hide", "weight": 1.0, "value": 5, "first": "Drain Fatigue", "second": "Fortify Endurance", "third": "Restore Personality", "fourth": "Fortify Luck", "ID": "ingred_guar_hide_marus"}, {"name": "Medium Corprusmeat Hunk", "weight": 0.5, "value": 0, "first": "Drain Fatigue", "second": "Drain Health", "third": "Drain Magicka", "fourth": null, "ID": "ingred_6th_corprusmeat_06"}, {"name": "Medium Wrapped Corprusmeat", "weight": 0.5, "value": 0, "first": "Drain Fatigue", "second": "Drain Health", "third": "Drain Magicka", "fourth": null, "ID": "ingred_6th_corprusmeat_03"}, {"name": "Meteor Slime", "weight": 0.1, "value": 10, "first": "Fortify Willpower", "second": "Cure Poison", "third": "Cure Blight Disease", "fourth": "Restore Willpower", "ID": "ingred_scrib_jelly_02"}, {"name": "Moon Sugar", "weight": 0.1, "value": 50, "first": "Fortify Speed", "second": "Dispel", "third": "Drain Endurance", "fourth": "Drain Luck", "ID": "ingred_moon_sugar_01"}, {"name": "Muck", "weight": 0.1, "value": 1, "first": "Drain Intelligence", "second": "Detect Key", "third": "Drain Personality", "fourth": "Cure Common Disease", "ID": "ingred_muck_01"}, {"name": "Muffin (Morrowind)", "weight": 0.2, "value": 1, "first": "Restore Fatigue", "second": null, "third": null, "fourth": null, "ID": "ingred_bread_01_UNI3"}, {"name": "Netch Leather", "weight": 1.0, "value": 1, "first": "Fortify Endurance", "second": "Fortify Intelligence", "third": "Drain Personality", "fourth": "Cure Paralyzation", "ID": "ingred_netch_leather_01"}, {"name": "Pearl", "weight": 0.2, "value": 100, "first": "Drain Agility", "second": "Dispel", "third": "Water Breathing", "fourth": "Resist Common Disease", "ID": "ingred_pearl_01, ingred_Dae_cursed_pearl_01"}, {"name": "Poison", "weight": 0.1, "value": 0, "first": "Weakness to Poison", "second": "Damage Health", "third": "Damage Fatigue", "fourth": "Poison", "ID": "poison_goop00"}, {"name": "Racer Plumes", "weight": 0.1, "value": 20, "first": "Drain Willpower", "second": "Levitate", "third": null, "fourth": null, "ID": "ingred_racer_plumes_01"}, {"name": "Rat Meat", "weight": 1.0, "value": 1, "first": "Drain Magicka", "second": "Paralyze", "third": "Cure Poison", "fourth": "Resist Poison", "ID": "ingred_rat_meat_01"}, {"name": "Raw Ebony", "weight": 10.0, "value": 200, "first": "Drain Agility", "second": "Cure Poison", "third": "Frost Shield", "fourth": "Restore Speed", "ID": "ingred_raw_ebony_01, ingred_Dae_cursed_raw_ebony_01"}, {"name": "Raw Glass", "weight": 2.0, "value": 200, "first": "Drain Intelligence", "second": "Drain Strength", "third": "Drain Speed", "fourth": "Fire Shield", "ID": "ingred_raw_glass_01, ingred_raw_glass_tinos"}, {"name": "Red Lichen", "weight": 0.1, "value": 25, "first": "Drain Speed", "second": "Light", "third": "Cure Common Disease", "fourth": "Drain Magicka", "ID": "ingred_red_lichen_01"}, {"name": "Resin", "weight": 0.1, "value": 10, "first": "Restore Health", "second": "Restore Speed", "third": "Burden", "fourth": "Resist Common Disease", "ID": "ingred_resin_01"}, {"name": "Roland's Tears", "weight": 0.1, "value": 5, "first": "Drain Health", "second": "Burden", "third": "Drain Luck", "fourth": "Restore Strength", "ID": "ingred_gold_kanet_unique"}, {"name": "Roobrush", "weight": 0.1, "value": 1, "first": "Drain Willpower", "second": "Fortify Agility", "third": "Drain Health", "fourth": "Cure Poison", "ID": "ingred_roobrush_01"}, {"name": "Ruby", "weight": 0.2, "value": 200, "first": "Drain Health", "second": "Feather", "third": "Restore Intelligence", "fourth": "Drain Agility", "ID": "ingred_ruby_01, ingred_Dae_cursed_ruby_01"}, {"name": "Saltrice", "weight": 0.1, "value": 1, "first": "Restore Fatigue", "second": "Fortify Magicka", "third": "Drain Strength", "fourth": "Restore Health", "ID": "ingred_saltrice_01"}, {"name": "Scales", "weight": 0.2, "value": 2, "first": "Drain Personality", "second": "Water Walking", "third": "Restore Endurance", "fourth": "Swift Swim", "ID": "ingred_scales_01"}, {"name": "Scamp Skin", "weight": 0.1, "value": 10, "first": "Drain Magicka", "second": "Cure Paralyzation", "third": "Restore Personality", "fourth": "Restore Strength", "ID": "ingred_scamp_skin_01"}, {"name": "Scathecraw", "weight": 0.1, "value": 2, "first": "Drain Strength", "second": "Cure Poison", "third": "Drain Health", "fourth": "Restore Willpower", "ID": "ingred_scathecraw_01"}, {"name": "Scrap Metal", "weight": 10.0, "value": 20, "first": "Drain Health", "second": "Lightning Shield", "third": "Resist Shock", "fourth": "Restore Intelligence", "ID": "ingred_scrap_metal_01"}, {"name": "Scrib Jelly", "weight": 0.1, "value": 10, "first": "Fortify Willpower", "second": "Cure Poison", "third": "Cure Blight Disease", "fourth": "Restore Willpower", "ID": "ingred_scrib_jelly_01"}, {"name": "Scrib Jerky", "weight": 0.2, "value": 5, "first": "Restore Fatigue", "second": "Fortify Fatigue", "third": "Burden", "fourth": "Swift Swim", "ID": "ingred_scrib_jerky_01"}, {"name": "Scuttle", "weight": 0.1, "value": 10, "first": "Restore Fatigue", "second": "Fortify Fatigue", "third": "Feather", "fourth": "Telekinesis", "ID": "ingred_scuttle_01"}, {"name": "Shalk Resin", "weight": 0.1, "value": 50, "first": "Drain Fatigue", "second": "Fortify Health", "third": "Drain Personality", "fourth": "Fortify Speed", "ID": "ingred_shalk_resin_01"}, {"name": "Sload Soap", "weight": 0.1, "value": 50, "first": "Drain Personality", "second": "Fortify Agility", "third": "Fire Shield", "fourth": "Restore Agility", "ID": "ingred_sload_soap_01"}, {"name": "Small Corprusmeat Hunk", "weight": 0.2, "value": 0, "first": "Drain Fatigue", "second": "Drain Health", "third": "Drain Magicka", "fourth": null, "ID": "ingred_6th_corprusmeat_07"}, {"name": "Small Kwama Egg", "weight": 0.5, "value": 1, "first": "Restore Fatigue", "second": null, "third": null, "fourth": null, "ID": "food_kwama_egg_01"}, {"name": "Small Wrapped Corprusmeat", "weight": 0.2, "value": 0, "first": "Drain Fatigue", "second": "Drain Health", "third": "Drain Magicka", "fourth": null, "ID": "ingred_6th_corprusmeat_02"}, {"name": "Spore Pod", "weight": 0.1, "value": 1, "first": "Drain Strength", "second": "Drain Fatigue", "third": "Detect Key", "fourth": "Paralyze", "ID": "ingred_bc_spore_pod"}, {"name": "Stoneflower Petals", "weight": 0.1, "value": 1, "first": "Restore Strength", "second": "Fortify Magicka", "third": "Drain Luck", "fourth": "Fortify Personality", "ID": "ingred_stoneflower_petals_01"}, {"name": "Trama Root", "weight": 0.1, "value": 10, "first": "Restore Willpower", "second": "Levitate", "third": "Drain Magicka", "fourth": "Drain Speed", "ID": "ingred_trama_root_01"}, {"name": "Treated Bittergreen Petals", "weight": 0.1, "value": 10, "first": "Restore Intelligence", "second": "Drain Magicka", "third": "Drain Endurance", "fourth": "Invisibility", "ID": "ingred_treated_bittergreen_uniq"}, {"name": "Vampire Dust", "weight": 0.1, "value": 500, "first": "Fortify Health", "second": "Fortify Strength", "third": "Spell Absorption", "fourth": "Vampirism", "ID": "ingred_vampire_dust_01"}, {"name": "Violet Coprinus", "weight": 0.5, "value": 1, "first": "Water Walking", "second": "Drain Fatigue", "third": "Poison", "fourth": null, "ID": "ingred_coprinus_01"}, {"name": "Void Salts", "weight": 0.1, "value": 100, "first": "Restore Magicka", "second": "Spell Absorption", "third": "Paralyze", "fourth": "Drain Endurance", "ID": "ingred_void_salts_01"}, {"name": "Wickwheat", "weight": 0.1, "value": 1, "first": "Restore Health", "second": "Fortify Willpower", "third": "Paralyze", "fourth": "Damage Intelligence", "ID": "ingred_wickwheat_01"}, {"name": "Willow Anther", "weight": 0.1, "value": 10, "first": "Drain Personality", "second": "Frost Shield", "third": "Cure Common Disease", "fourth": "Cure Paralyzation", "ID": "ingred_willow_anther_01"}, {"name": "Wrapped Corprusmeat Hunk", "weight": 0.0, "value": 0, "first": "Drain Fatigue", "second": "Drain Health", "third": "Drain Magicka", "fourth": null, "ID": "ingred_6th_corprusmeat_04"}, {"name": "Bear Pelt", "weight": 1.0, "value": 2, "first": "Drain Fatigue", "second": "Fortify Strength", "third": "Resist Common Disease", "fourth": null, "ID": "ingred_bear_pelt"}, {"name": "Blood of an Innocent", "weight": 0.1, "value": 25, "first": "Drain Speed (Morrowind)", "second": "Light", "third": "Cure Common Disease", "fourth": "Drain Magicka (Morrowind)", "ID": "ingred_blood_innocent_unique"}, {"name": "Bristleback Leather", "weight": 1.0, "value": 2, "first": "Blind", "second": "Frost Damage", "third": "Resist Frost", "fourth": "Recall", "ID": "ingred_boar_leather"}, {"name": "Flaming Eye of the Lightkeeper", "weight": 1.0, "value": 15, "first": "Resist Frost", "second": null, "third": "Drain Magicka (Morrowind)", "fourth": "Fortify Strength", "ID": "ingred_eyeball_unique"}, {"name": "Grahl Eyeball", "weight": 1.0, "value": 15, "first": "Resist Frost", "second": null, "third": "Drain Magicka (Morrowind)", "fourth": "Fortify Strength", "ID": "ingred_eyeball"}, {"name": "Gravetar", "weight": 0.1, "value": 5, "first": "Resist Frost", "second": "Drain Health", "third": "Fortify Fatigue", "fourth": "Drain Luck (Morrowind)", "ID": "ingred_gravetar_01"}, {"name": "Heart of an Innocent", "weight": 1.0, "value": 10, "first": "Magicka", "second": "Fortify Endurance", "third": "Drain Agility (Morrowind)", "fourth": null, "ID": "ingred_innocent_heart"}, {"name": "Heart of the Udyrfrykte", "weight": 5.0, "value": 300, "first": "Magicka", "second": "Fortify Endurance", "third": "Drain Agility (Morrowind)", "fourth": null, "ID": "ingred_udyrfrykte_heart"}, {"name": "Heart of the Wolf", "weight": 1.0, "value": 100, "first": "Magicka", "second": "Fortify Endurance", "third": "Drain Agility (Morrowind)", "fourth": null, "ID": "ingred_wolf_heart"}, {"name": "Heartwood", "weight": 1.0, "value": 200, "first": "Magicka", "second": "Fortify Agility", "third": "Drain Strength (Morrowind)", "fourth": "Weakness to Fire Damage (Morrowind)", "ID": "ingred_heartwood_01"}, {"name": "Holly Berries", "weight": 0.1, "value": 5, "first": "Resist Frost", "second": "Resist Poison", "third": "Frost Damage", "fourth": "Weakness to Fire Damage (Morrowind)", "ID": "ingred_holly_01"}, {"name": "Horker Tusk", "weight": 1.0, "value": 5, "first": "Drain Alteration (Morrowind)", "second": "Fortify Intelligence", "third": "Fortify Maximum Magicka", "fourth": "Detect Animal", "ID": "ingred_horker_tusk_01"}, {"name": "Pinetear", "weight": 0.2, "value": 50, "first": "Fortify Magicka", "second": "Restore Health", "third": "Drain Agility (Morrowind)", "fourth": "Drain Endurance (Morrowind)", "ID": "ingred_emerald_pinetear_01"}, {"name": "Raw Stalhrim", "weight": 0.5, "value": 300, "first": "Resist Frost", "second": "Frost Damage", "third": "Paralyze", "fourth": "Restore Health", "ID": "ingred_raw_Stalhrim_01"}, {"name": "Ripened Belladonna Berries", "weight": 0.1, "value": 5, "first": "Resist Magicka (Morrowind)", "second": "Magicka", "third": "Fortify Magicka", "fourth": "Drain Magicka (Morrowind)", "ID": "ingred_belladonna_01"}, {"name": "Snow Bear Pelt", "weight": 1.0, "value": 2, "first": "Drain Fatigue", "second": "Fortify Strength", "third": "Resist Common Disease", "fourth": null, "ID": "ingred_snowbear_pelt_unique"}, {"name": "Snow Wolf Pelt", "weight": 1.0, "value": 2, "first": "Drain Fatigue", "second": "Fortify Strength", "third": "Resist Common Disease", "fourth": null, "ID": "ingred_snowwolf_pelt_unique"}, {"name": "Unripened Belladonna Berries", "weight": 0.1, "value": 5, "first": "Resist Magicka (Morrowind)", "second": "Magicka", "third": "Fortify Magicka", "fourth": "Drain Magicka (Morrowind)", "ID": "ingred_belladonna_02"}, {"name": "Wolf Pelt", "weight": 1.0, "value": 2, "first": "Drain Fatigue", "second": "Fortify Strength", "third": "Resist Common Disease", "fourth": null, "ID": "ingred_wolf_pelt"}, {"name": "Wolfsbane Petals", "weight": 0.1, "value": 5, "first": "Intelligence", "second": "Invisibility", "third": "Drain Endurance (Morrowind)", "fourth": "Drain Magicka (Morrowind)", "ID": "ingred_wolfsbane_01"}, {"name": "Adamantium Ore", "weight": 50.0, "value": 300, "first": "Burden", "second": "Magicka", "third": "Poison", "fourth": "Reflect", "ID": "ingred_adamantium_ore_01"}, {"name": "Durzog Meat", "weight": 2.0, "value": 7, "first": "Fortify Agility", "second": "Fortify Strength", "third": "Blind", "fourth": "Damage Magicka (Morrowind)", "ID": "ingred_durzog_meat_01"}, {"name": "Golden Sedge Flowers", "weight": 1.0, "value": 1, "first": "Drain Magicka", "second": "Fortify Strength", "third": "Fortify Attack", "fourth": "Swift Swim", "ID": "ingred_golden_sedge_01"}, {"name": "Horn Lily Bulb", "weight": 1.0, "value": 1, "first": "Resist Paralyze (Morrowind)", "second": "Drain Health", "third": "Strength", "fourth": "Endurance", "ID": "ingred_horn_lily_bulb_01"}, {"name": "Lloramor Spines", "weight": 1.0, "value": 1, "first": "Spell Absorption", "second": "Invisibility", "third": "Poison", "fourth": "Detect Enchantment", "ID": "ingred_lloramor_spines_01"}, {"name": "Meadow Rye", "weight": 1.0, "value": 1, "first": "Fortify Speed", "second": "Damage Health (Morrowind)", "third": "Speed", "fourth": "Drain Speed (Morrowind)", "ID": "ingred_meadow_rye_01"}, {"name": "Nirthfly Stalks", "weight": 1.0, "value": 1, "first": "Damage Health (Morrowind)", "second": "Fortify Speed", "third": "Speed", "fourth": "Drain Speed (Morrowind)", "ID": "ingred_nirthfly_stalks_01"}, {"name": "Noble Sedge Flowers", "weight": 1.0, "value": 1, "first": "Damage Health (Morrowind)", "second": "Agility", "third": "Poison", "fourth": "Fortify Agility", "ID": "ingred_noble_sedge_01"}, {"name": "Scrib Cabbage", "weight": 1.0, "value": 1, "first": "Drain Intelligence (Morrowind)", "second": "Damage Health (Morrowind)", "third": "Agility", "fourth": "Fortify Agility", "ID": "ingred_scrib_cabbage_01"}, {"name": "Sweetpulp", "weight": 1.0, "value": 1, "first": "Paralyze", "second": "Levitate", "third": "Resist Paralyze (Morrowind)", "fourth": "Restore Health (Morrowind)", "ID": "ingred_sweetpulp_01"}, {"name": "Timsa-Come-By Flowers", "weight": 1.0, "value": 1, "first": "Dispel", "second": "Resist Paralyze (Morrowind)", "third": "Drain Magicka (Morrowind)", "fourth": "Endurance", "ID": "ingred_timsa-come-by_01"}]