[{"name": "Abecean Longfin", "effect": "Weakness to Frost", "base_magnitude": 3, "base_cost": 0.5}, {"name": "Abecean Longfin", "effect": "Fortify Sneak", "base_magnitude": 4, "base_cost": 0.5}, {"name": "Abecean Longfin", "effect": "Weakness to Poison", "base_magnitude": 2, "base_cost": 1.0}, {"name": "Abecean Longfin", "effect": "Fortify Restoration", "base_magnitude": 4, "base_cost": 0.5}, {"name": "Bear Claws", "effect": "Restore Stamina", "base_magnitude": 5, "base_cost": 0.6}, {"name": "Bear Claws", "effect": "Fortify Health", "base_magnitude": 4, "base_cost": 0.35}, {"name": "Bear Claws", "effect": "Fortify One-Handed", "base_magnitude": 4, "base_cost": 0.5}, {"name": "Bear Claws", "effect": "Damage Magicka Regen", "base_magnitude": 100, "base_cost": 0.5}, {"name": "Bee", "effect": "Restore Stamina", "base_magnitude": 5, "base_cost": 0.6}, {"name": "Bee", "effect": "Ravage Stamina", "base_magnitude": 2, "base_cost": 1.6}, {"name": "Bee", "effect": "Regenerate Stamina", "base_magnitude": 5, "base_cost": 0.1}, {"name": "Bee", "effect": "Weakness to Shock", "base_magnitude": 3, "base_cost": 0.7}, {"name": "Beehive Husk", "effect": "Resist Poison", "base_magnitude": 4, "base_cost": 0.5}, {"name": "Beehive Husk", "effect": "Fortify Light Armor", "base_magnitude": 2, "base_cost": 0.5}, {"name": "Beehive Husk", "effect": "Fortify Sneak", "base_magnitude": 4, "base_cost": 0.5}, {"name": "Beehive Husk", "effect": "Fortify Destruction", "base_magnitude": 5, "base_cost": 0.5}, {"name": "Berit's Ashes", "effect": "Damage Stamina", "base_magnitude": 3, "base_cost": 1.8}, {"name": "Berit's Ashes", "effect": "Resist Fire", "base_magnitude": 3, "base_cost": 0.5}, {"name": "Berit's Ashes", "effect": "Fortify Conjuration", "base_magnitude": 5, "base_cost": 0.25}, {"name": "Berit's Ashes", "effect": "Ravage Stamina", "base_magnitude": 2, "base_cost": 1.6}, {"name": "Bleeding Crown", "effect": "Weakness to Fire", "base_magnitude": 3, "base_cost": 0.6}, {"name": "Bleeding Crown", "effect": "Fortify Block", "base_magnitude": 4, "base_cost": 0.5}, {"name": "Bleeding Crown", "effect": "Weakness to Poison", "base_magnitude": 2, "base_cost": 1.0}, {"name": "Bleeding Crown", "effect": "Resist Magic", "base_magnitude": 1, "base_cost": 1.0}, {"name": "Blisterwort", "effect": "Damage Stamina", "base_magnitude": 3, "base_cost": 1.8}, {"name": "Blisterwort", "effect": "Frenzy", "base_magnitude": 1, "base_cost": 15.0}, {"name": "Blisterwort", "effect": "Restore Health", "base_magnitude": 5, "base_cost": 0.5}, {"name": "Blisterwort", "effect": "Fortify Smithing", "base_magnitude": 4, "base_cost": 0.75}, {"name": "Blue Butterfly Wing", "effect": "Damage Stamina", "base_magnitude": 3, "base_cost": 1.8}, {"name": "Blue Butterfly Wing", "effect": "Fortify Conjuration", "base_magnitude": 5, "base_cost": 0.25}, {"name": "Blue Butterfly Wing", "effect": "Damage Magicka Regen", "base_magnitude": 100, "base_cost": 0.5}, {"name": "Blue Butterfly Wing", "effect": "Fortify Enchanting", "base_magnitude": 1, "base_cost": 0.6}, {"name": "Blue Dartwing", "effect": "Resist Shock", "base_magnitude": 3, "base_cost": 0.5}, {"name": "Blue Dartwing", "effect": "Fortify Pickpocket", "base_magnitude": 4, "base_cost": 0.5}, {"name": "Blue Dartwing", "effect": "Restore Health", "base_magnitude": 5, "base_cost": 0.5}, {"name": "Blue Dartwing", "effect": "Fear", "base_magnitude": 1, "base_cost": 5.0}, {"name": "Blue Mountain Flower", "effect": "Restore Health", "base_magnitude": 5, "base_cost": 0.5}, {"name": "Blue Mountain Flower", "effect": "Fortify Conjuration", "base_magnitude": 5, "base_cost": 0.25}, {"name": "Blue Mountain Flower", "effect": "Fortify Health", "base_magnitude": 4, "base_cost": 0.35}, {"name": "Blue Mountain Flower", "effect": "Damage Magicka Regen", "base_magnitude": 100, "base_cost": 0.5}, {"name": "Bone Meal", "effect": "Damage Stamina", "base_magnitude": 3, "base_cost": 1.8}, {"name": "Bone Meal", "effect": "Resist Fire", "base_magnitude": 3, "base_cost": 0.5}, {"name": "Bone Meal", "effect": "Fortify Conjuration", "base_magnitude": 5, "base_cost": 0.25}, {"name": "Bone Meal", "effect": "Ravage Stamina", "base_magnitude": 2, "base_cost": 1.6}, {"name": "Briar Heart", "effect": "Restore Magicka", "base_magnitude": 5, "base_cost": 0.6}, {"name": "Briar Heart", "effect": "Fortify Block", "base_magnitude": 4, "base_cost": 0.5}, {"name": "Briar Heart", "effect": "Paralysis", "base_magnitude": 0, "base_cost": 500.0}, {"name": "Briar Heart", "effect": "Fortify Magicka", "base_magnitude": 4, "base_cost": 0.3}, {"name": "Butterfly Wing", "effect": "Restore Health", "base_magnitude": 5, "base_cost": 0.5}, {"name": "Butterfly Wing", "effect": "Fortify Barter", "base_magnitude": 1, "base_cost": 2.0}, {"name": "Butterfly Wing", "effect": "Lingering Damage Stamina", "base_magnitude": 1, "base_cost": 1.8}, {"name": "Butterfly Wing", "effect": "Damage Magicka", "base_magnitude": 3, "base_cost": 2.2}, {"name": "Canis Root", "effect": "Damage Stamina", "base_magnitude": 3, "base_cost": 1.8}, {"name": "Canis Root", "effect": "Fortify One-Handed", "base_magnitude": 4, "base_cost": 0.5}, {"name": "Canis Root", "effect": "Fortify Marksman", "base_magnitude": 4, "base_cost": 0.5}, {"name": "Canis Root", "effect": "Paralysis", "base_magnitude": 0, "base_cost": 500.0}, {"name": "Charred Skeever Hide", "effect": "Restore Stamina", "base_magnitude": 5, "base_cost": 0.6}, {"name": "Charred Skeever Hide", "effect": "Cure Disease", "base_magnitude": 5, "base_cost": 0.5}, {"name": "Charred Skeever Hide", "effect": "Resist Poison", "base_magnitude": 4, "base_cost": 0.5}, {"name": "Charred Skeever Hide", "effect": "Restore Health", "base_magnitude": 5, "base_cost": 0.5}, {"name": "Chaurus Eggs", "effect": "Weakness to Poison", "base_magnitude": 2, "base_cost": 1.0}, {"name": "Chaurus Eggs", "effect": "Fortify Stamina", "base_magnitude": 4, "base_cost": 0.3}, {"name": "Chaurus Eggs", "effect": "Damage Magicka", "base_magnitude": 3, "base_cost": 2.2}, {"name": "Chaurus Eggs", "effect": "Invisibility", "base_magnitude": 0, "base_cost": 100.0}, {"name": "Chicken's Egg", "effect": "Resist Magic", "base_magnitude": 1, "base_cost": 1.0}, {"name": "Chicken's Egg", "effect": "Damage Magicka Regen", "base_magnitude": 100, "base_cost": 0.5}, {"name": "Chicken's Egg", "effect": "Waterbreathing", "base_magnitude": 0, "base_cost": 30.0}, {"name": "Chicken's Egg", "effect": "Lingering Damage Stamina", "base_magnitude": 1, "base_cost": 1.8}, {"name": "Creep Cluster", "effect": "Restore Magicka", "base_magnitude": 5, "base_cost": 0.6}, {"name": "Creep Cluster", "effect": "Damage Stamina Regen", "base_magnitude": 100, "base_cost": 0.3}, {"name": "Creep Cluster", "effect": "Fortify Carry Weight", "base_magnitude": 4, "base_cost": 0.15}, {"name": "Creep Cluster", "effect": "Weakness to Magic", "base_magnitude": 2, "base_cost": 1.0}, {"name": "Crimson Nirnroot", "effect": "Damage Health", "base_magnitude": 2, "base_cost": 3.0}, {"name": "Crimson Nirnroot", "effect": "Damage Stamina", "base_magnitude": 3, "base_cost": 1.8}, {"name": "Crimson Nirnroot", "effect": "Invisibility", "base_magnitude": 0, "base_cost": 100.0}, {"name": "Crimson Nirnroot", "effect": "Resist Magic", "base_magnitude": 1, "base_cost": 1.0}, {"name": "Cyrodilic Spadetail", "effect": "Damage Stamina", "base_magnitude": 3, "base_cost": 1.8}, {"name": "Cyrodilic Spadetail", "effect": "Fortify Restoration", "base_magnitude": 4, "base_cost": 0.5}, {"name": "Cyrodilic Spadetail", "effect": "Fear", "base_magnitude": 1, "base_cost": 5.0}, {"name": "Cyrodilic Spadetail", "effect": "Ravage Health", "base_magnitude": 2, "base_cost": 0.4}, {"name": "Daedra Heart", "effect": "Restore Health", "base_magnitude": 5, "base_cost": 0.5}, {"name": "Daedra Heart", "effect": "Damage Stamina Regen", "base_magnitude": 100, "base_cost": 0.3}, {"name": "Daedra Heart", "effect": "Damage Magicka", "base_magnitude": 3, "base_cost": 2.2}, {"name": "Daedra Heart", "effect": "Fear", "base_magnitude": 1, "base_cost": 5.0}, {"name": "Deathbell", "effect": "Damage Health", "base_magnitude": 2, "base_cost": 3.0}, {"name": "Deathbell", "effect": "Ravage Stamina", "base_magnitude": 2, "base_cost": 1.6}, {"name": "Deathbell", "effect": "Slow", "base_magnitude": 50, "base_cost": 1.0}, {"name": "Deathbell", "effect": "Weakness to Poison", "base_magnitude": 2, "base_cost": 1.0}, {"name": "Dragon's Tongue", "effect": "Resist Fire", "base_magnitude": 3, "base_cost": 0.5}, {"name": "Dragon's Tongue", "effect": "Fortify Barter", "base_magnitude": 1, "base_cost": 2.0}, {"name": "Dragon's Tongue", "effect": "Fortify Illusion", "base_magnitude": 4, "base_cost": 0.4}, {"name": "Dragon's Tongue", "effect": "Fortify Two-Handed", "base_magnitude": 4, "base_cost": 0.5}, {"name": "Dwarven Oil", "effect": "Weakness to Magic", "base_magnitude": 2, "base_cost": 1.0}, {"name": "Dwarven Oil", "effect": "Fortify Illusion", "base_magnitude": 4, "base_cost": 0.4}, {"name": "Dwarven Oil", "effect": "Regenerate Magicka", "base_magnitude": 5, "base_cost": 0.1}, {"name": "Dwarven Oil", "effect": "Restore Magicka", "base_magnitude": 5, "base_cost": 0.6}, {"name": "Ectoplasm", "effect": "Restore Magicka", "base_magnitude": 5, "base_cost": 0.6}, {"name": "Ectoplasm", "effect": "Fortify Destruction", "base_magnitude": 5, "base_cost": 0.5}, {"name": "Ectoplasm", "effect": "Fortify Magicka", "base_magnitude": 4, "base_cost": 0.3}, {"name": "Ectoplasm", "effect": "Damage Health", "base_magnitude": 2, "base_cost": 3.0}, {"name": "Elves Ear", "effect": "Restore Magicka", "base_magnitude": 5, "base_cost": 0.6}, {"name": "Elves Ear", "effect": "Fortify Marksman", "base_magnitude": 4, "base_cost": 0.5}, {"name": "Elves Ear", "effect": "Weakness to Frost", "base_magnitude": 3, "base_cost": 0.5}, {"name": "Elves Ear", "effect": "Resist Fire", "base_magnitude": 3, "base_cost": 0.5}, {"name": "Eye of Sabre Cat", "effect": "Restore Stamina", "base_magnitude": 5, "base_cost": 0.6}, {"name": "Eye of Sabre Cat", "effect": "Ravage Health", "base_magnitude": 2, "base_cost": 0.4}, {"name": "Eye of Sabre Cat", "effect": "Damage Magicka", "base_magnitude": 3, "base_cost": 2.2}, {"name": "Eye of Sabre Cat", "effect": "Restore Health", "base_magnitude": 5, "base_cost": 0.5}, {"name": "Falmer Ear", "effect": "Damage Health", "base_magnitude": 2, "base_cost": 3.0}, {"name": "Falmer Ear", "effect": "Frenzy", "base_magnitude": 1, "base_cost": 15.0}, {"name": "Falmer Ear", "effect": "Resist Poison", "base_magnitude": 4, "base_cost": 0.5}, {"name": "Falmer Ear", "effect": "Fortify Lockpicking", "base_magnitude": 2, "base_cost": 0.5}, {"name": "Fine-Cut Void Salts", "effect": "Weakness to Shock", "base_magnitude": 3, "base_cost": 0.7}, {"name": "Fine-Cut Void Salts", "effect": "Resist Magic", "base_magnitude": 1, "base_cost": 1.0}, {"name": "Fine-Cut Void Salts", "effect": "Damage Health", "base_magnitude": 2, "base_cost": 3.0}, {"name": "Fine-Cut Void Salts", "effect": "Fortify Magicka", "base_magnitude": 4, "base_cost": 0.3}, {"name": "Fire Salts", "effect": "Weakness to Frost", "base_magnitude": 3, "base_cost": 0.5}, {"name": "Fire Salts", "effect": "Resist Fire", "base_magnitude": 3, "base_cost": 0.5}, {"name": "Fire Salts", "effect": "Restore Magicka", "base_magnitude": 5, "base_cost": 0.6}, {"name": "Fire Salts", "effect": "Regenerate Magicka", "base_magnitude": 5, "base_cost": 0.1}, {"name": "Fly Amanita", "effect": "Resist Fire", "base_magnitude": 3, "base_cost": 0.5}, {"name": "Fly Amanita", "effect": "Fortify Two-Handed", "base_magnitude": 4, "base_cost": 0.5}, {"name": "Fly Amanita", "effect": "Frenzy", "base_magnitude": 1, "base_cost": 15.0}, {"name": "Fly Amanita", "effect": "Regenerate Stamina", "base_magnitude": 5, "base_cost": 0.1}, {"name": "Frost Mirriam", "effect": "Resist Frost", "base_magnitude": 3, "base_cost": 0.5}, {"name": "Frost Mirriam", "effect": "Fortify Sneak", "base_magnitude": 4, "base_cost": 0.5}, {"name": "Frost Mirriam", "effect": "Ravage Magicka", "base_magnitude": 2, "base_cost": 1.0}, {"name": "Frost Mirriam", "effect": "Damage Stamina Regen", "base_magnitude": 100, "base_cost": 0.3}, {"name": "Frost Salts", "effect": "Weakness to Fire", "base_magnitude": 3, "base_cost": 0.6}, {"name": "Frost Salts", "effect": "Resist Frost", "base_magnitude": 3, "base_cost": 0.5}, {"name": "Frost Salts", "effect": "Restore Magicka", "base_magnitude": 5, "base_cost": 0.6}, {"name": "Frost Salts", "effect": "Fortify Conjuration", "base_magnitude": 5, "base_cost": 0.25}, {"name": "Garlic", "effect": "Resist Poison", "base_magnitude": 4, "base_cost": 0.5}, {"name": "Garlic", "effect": "Fortify Stamina", "base_magnitude": 4, "base_cost": 0.3}, {"name": "Garlic", "effect": "Regenerate Magicka", "base_magnitude": 5, "base_cost": 0.1}, {"name": "Garlic", "effect": "Regenerate Health", "base_magnitude": 5, "base_cost": 0.1}, {"name": "Giant Lichen", "effect": "Weakness to Shock", "base_magnitude": 3, "base_cost": 0.7}, {"name": "Giant Lichen", "effect": "Ravage Health", "base_magnitude": 2, "base_cost": 0.4}, {"name": "Giant Lichen", "effect": "Weakness to Poison", "base_magnitude": 2, "base_cost": 1.0}, {"name": "Giant Lichen", "effect": "Restore Magicka", "base_magnitude": 5, "base_cost": 0.6}, {"name": "Giant's Toe", "effect": "Damage Stamina", "base_magnitude": 3, "base_cost": 1.8}, {"name": "Giant's Toe", "effect": "Fortify Health", "base_magnitude": 4, "base_cost": 0.35}, {"name": "Giant's Toe", "effect": "Fortify Carry Weight", "base_magnitude": 4, "base_cost": 0.15}, {"name": "Giant's Toe", "effect": "Damage Stamina Regen", "base_magnitude": 100, "base_cost": 0.3}, {"name": "Glow Dust", "effect": "Damage Magicka", "base_magnitude": 3, "base_cost": 2.2}, {"name": "Glow Dust", "effect": "Damage Magicka Regen", "base_magnitude": 100, "base_cost": 0.5}, {"name": "Glow Dust", "effect": "Fortify Destruction", "base_magnitude": 5, "base_cost": 0.5}, {"name": "Glow Dust", "effect": "Resist Shock", "base_magnitude": 3, "base_cost": 0.5}, {"name": "Glowing Mushroom", "effect": "Resist Shock", "base_magnitude": 3, "base_cost": 0.5}, {"name": "Glowing Mushroom", "effect": "Fortify Destruction", "base_magnitude": 5, "base_cost": 0.5}, {"name": "Glowing Mushroom", "effect": "Fortify Smithing", "base_magnitude": 4, "base_cost": 0.75}, {"name": "Glowing Mushroom", "effect": "Fortify Health", "base_magnitude": 4, "base_cost": 0.35}, {"name": "Grass Pod", "effect": "Resist Poison", "base_magnitude": 4, "base_cost": 0.5}, {"name": "Grass Pod", "effect": "Ravage Magicka", "base_magnitude": 2, "base_cost": 1.0}, {"name": "Grass Pod", "effect": "Fortify Alteration", "base_magnitude": 4, "base_cost": 0.2}, {"name": "Grass Pod", "effect": "Restore Magicka", "base_magnitude": 5, "base_cost": 0.6}, {"name": "Hagraven Claw", "effect": "Resist Magic", "base_magnitude": 1, "base_cost": 1.0}, {"name": "Hagraven Claw", "effect": "Lingering Damage Magicka", "base_magnitude": 1, "base_cost": 10.0}, {"name": "Hagraven Claw", "effect": "Fortify Enchanting", "base_magnitude": 1, "base_cost": 0.6}, {"name": "Hagraven Claw", "effect": "Fortify Barter", "base_magnitude": 1, "base_cost": 2.0}, {"name": "Hagraven Feathers", "effect": "Damage Magicka", "base_magnitude": 3, "base_cost": 2.2}, {"name": "Hagraven Feathers", "effect": "Fortify Conjuration", "base_magnitude": 5, "base_cost": 0.25}, {"name": "Hagraven Feathers", "effect": "Frenzy", "base_magnitude": 1, "base_cost": 15.0}, {"name": "Hagraven Feathers", "effect": "Weakness to Shock", "base_magnitude": 3, "base_cost": 0.7}, {"name": "Hanging Moss", "effect": "Damage Magicka", "base_magnitude": 3, "base_cost": 2.2}, {"name": "Hanging Moss", "effect": "Fortify Health", "base_magnitude": 4, "base_cost": 0.35}, {"name": "Hanging Moss", "effect": "Damage Magicka Regen", "base_magnitude": 100, "base_cost": 0.5}, {"name": "Hanging Moss", "effect": "Fortify One-Handed", "base_magnitude": 4, "base_cost": 0.5}, {"name": "Hawk Beak", "effect": "Restore Stamina", "base_magnitude": 5, "base_cost": 0.6}, {"name": "Hawk Beak", "effect": "Resist Frost", "base_magnitude": 3, "base_cost": 0.5}, {"name": "Hawk Beak", "effect": "Fortify Carry Weight", "base_magnitude": 4, "base_cost": 0.15}, {"name": "Hawk Beak", "effect": "Resist Shock", "base_magnitude": 3, "base_cost": 0.5}, {"name": "Hawk Feathers", "effect": "Cure Disease", "base_magnitude": 5, "base_cost": 0.5}, {"name": "Hawk Feathers", "effect": "Fortify Light Armor", "base_magnitude": 2, "base_cost": 0.5}, {"name": "Hawk Feathers", "effect": "Fortify One-Handed", "base_magnitude": 4, "base_cost": 0.5}, {"name": "Hawk Feathers", "effect": "Fortify Sneak", "base_magnitude": 4, "base_cost": 0.5}, {"name": "Histcarp", "effect": "Restore Stamina", "base_magnitude": 5, "base_cost": 0.6}, {"name": "Histcarp", "effect": "Fortify Magicka", "base_magnitude": 4, "base_cost": 0.3}, {"name": "Histcarp", "effect": "Damage Stamina Regen", "base_magnitude": 100, "base_cost": 0.3}, {"name": "Histcarp", "effect": "Waterbreathing", "base_magnitude": 0, "base_cost": 30.0}, {"name": "Honeycomb", "effect": "Restore Stamina", "base_magnitude": 5, "base_cost": 0.6}, {"name": "Honeycomb", "effect": "Fortify Block", "base_magnitude": 4, "base_cost": 0.5}, {"name": "Honeycomb", "effect": "Fortify Light Armor", "base_magnitude": 2, "base_cost": 0.5}, {"name": "Honeycomb", "effect": "Ravage Stamina", "base_magnitude": 2, "base_cost": 1.6}, {"name": "Human Flesh", "effect": "Damage Health", "base_magnitude": 2, "base_cost": 3.0}, {"name": "Human Flesh", "effect": "Paralysis", "base_magnitude": 0, "base_cost": 500.0}, {"name": "Human Flesh", "effect": "Restore Magicka", "base_magnitude": 5, "base_cost": 0.6}, {"name": "Human Flesh", "effect": "Fortify Sneak", "base_magnitude": 4, "base_cost": 0.5}, {"name": "Human Heart", "effect": "Damage Health", "base_magnitude": 2, "base_cost": 3.0}, {"name": "Human Heart", "effect": "Damage Magicka", "base_magnitude": 3, "base_cost": 2.2}, {"name": "Human Heart", "effect": "Damage Magicka Regen", "base_magnitude": 100, "base_cost": 0.5}, {"name": "Human Heart", "effect": "Frenzy", "base_magnitude": 1, "base_cost": 15.0}, {"name": "Ice Wraith Teeth", "effect": "Weakness to Frost", "base_magnitude": 3, "base_cost": 0.5}, {"name": "Ice Wraith Teeth", "effect": "Fortify Heavy Armor", "base_magnitude": 2, "base_cost": 0.5}, {"name": "Ice Wraith Teeth", "effect": "Invisibility", "base_magnitude": 0, "base_cost": 100.0}, {"name": "Ice Wraith Teeth", "effect": "Weakness to Fire", "base_magnitude": 3, "base_cost": 0.6}, {"name": "Imp Stool", "effect": "Damage Health", "base_magnitude": 2, "base_cost": 3.0}, {"name": "Imp Stool", "effect": "Lingering Damage Health", "base_magnitude": 1, "base_cost": 12.0}, {"name": "Imp Stool", "effect": "Paralysis", "base_magnitude": 0, "base_cost": 500.0}, {"name": "Imp Stool", "effect": "Restore Health", "base_magnitude": 5, "base_cost": 0.5}, {"name": "Jarrin Root", "effect": "Damage Health", "base_magnitude": 2, "base_cost": 3.0}, {"name": "Jarrin Root", "effect": "Damage Magicka", "base_magnitude": 3, "base_cost": 2.2}, {"name": "Jarrin Root", "effect": "Damage Stamina", "base_magnitude": 3, "base_cost": 1.8}, {"name": "Jarrin Root", "effect": "Damage Magicka Regen", "base_magnitude": 100, "base_cost": 0.5}, {"name": "Jazbay Grapes", "effect": "Weakness to Magic", "base_magnitude": 2, "base_cost": 1.0}, {"name": "Jazbay Grapes", "effect": "Fortify Magicka", "base_magnitude": 4, "base_cost": 0.3}, {"name": "Jazbay Grapes", "effect": "Regenerate Magicka", "base_magnitude": 5, "base_cost": 0.1}, {"name": "Jazbay Grapes", "effect": "Ravage Health", "base_magnitude": 2, "base_cost": 0.4}, {"name": "Juniper Berries", "effect": "Weakness to Fire", "base_magnitude": 3, "base_cost": 0.6}, {"name": "Juniper Berries", "effect": "Fortify Marksman", "base_magnitude": 4, "base_cost": 0.5}, {"name": "Juniper Berries", "effect": "Regenerate Health", "base_magnitude": 5, "base_cost": 0.1}, {"name": "Juniper Berries", "effect": "Damage Stamina Regen", "base_magnitude": 100, "base_cost": 0.3}, {"name": "Large Antlers", "effect": "Restore Stamina", "base_magnitude": 5, "base_cost": 0.6}, {"name": "Large Antlers", "effect": "Fortify Stamina", "base_magnitude": 4, "base_cost": 0.3}, {"name": "Large Antlers", "effect": "Slow", "base_magnitude": 50, "base_cost": 1.0}, {"name": "Large Antlers", "effect": "Damage Stamina Regen", "base_magnitude": 100, "base_cost": 0.3}, {"name": "Lavender", "effect": "Resist Magic", "base_magnitude": 1, "base_cost": 1.0}, {"name": "Lavender", "effect": "Fortify Stamina", "base_magnitude": 4, "base_cost": 0.3}, {"name": "Lavender", "effect": "Ravage Magicka", "base_magnitude": 2, "base_cost": 1.0}, {"name": "Lavender", "effect": "Fortify Conjuration", "base_magnitude": 5, "base_cost": 0.25}, {"name": "Luna Moth Wing", "effect": "Damage Magicka", "base_magnitude": 3, "base_cost": 2.2}, {"name": "Luna Moth Wing", "effect": "Fortify Light Armor", "base_magnitude": 2, "base_cost": 0.5}, {"name": "Luna Moth Wing", "effect": "Regenerate Health", "base_magnitude": 5, "base_cost": 0.1}, {"name": "Luna Moth Wing", "effect": "Invisibility", "base_magnitude": 0, "base_cost": 100.0}, {"name": "Moon Sugar", "effect": "Weakness to Fire", "base_magnitude": 3, "base_cost": 0.6}, {"name": "Moon Sugar", "effect": "Resist Frost", "base_magnitude": 3, "base_cost": 0.5}, {"name": "Moon Sugar", "effect": "Restore Magicka", "base_magnitude": 5, "base_cost": 0.6}, {"name": "Moon Sugar", "effect": "Regenerate Magicka", "base_magnitude": 5, "base_cost": 0.1}, {"name": "Mora Tapinella", "effect": "Restore Magicka", "base_magnitude": 5, "base_cost": 0.6}, {"name": "Mora Tapinella", "effect": "Lingering Damage Health", "base_magnitude": 1, "base_cost": 12.0}, {"name": "Mora Tapinella", "effect": "Regenerate Stamina", "base_magnitude": 5, "base_cost": 0.1}, {"name": "Mora Tapinella", "effect": "Fortify Illusion", "base_magnitude": 4, "base_cost": 0.4}, {"name": "Mudcrab Chitin", "effect": "Restore Stamina", "base_magnitude": 5, "base_cost": 0.6}, {"name": "Mudcrab Chitin", "effect": "Cure Disease", "base_magnitude": 5, "base_cost": 0.5}, {"name": "Mudcrab Chitin", "effect": "Resist Poison", "base_magnitude": 4, "base_cost": 0.5}, {"name": "Mudcrab Chitin", "effect": "Resist Fire", "base_magnitude": 3, "base_cost": 0.5}, {"name": "Namira's Rot", "effect": "Damage Magicka", "base_magnitude": 3, "base_cost": 2.2}, {"name": "Namira's Rot", "effect": "Fortify Lockpicking", "base_magnitude": 2, "base_cost": 0.5}, {"name": "Namira's Rot", "effect": "Fear", "base_magnitude": 1, "base_cost": 5.0}, {"name": "Namira's Rot", "effect": "Regenerate Health", "base_magnitude": 5, "base_cost": 0.1}, {"name": "Nightshade", "effect": "Damage Health", "base_magnitude": 2, "base_cost": 3.0}, {"name": "Nightshade", "effect": "Damage Magicka Regen", "base_magnitude": 100, "base_cost": 0.5}, {"name": "Nightshade", "effect": "Lingering Damage Stamina", "base_magnitude": 1, "base_cost": 1.8}, {"name": "Nightshade", "effect": "Fortify Destruction", "base_magnitude": 5, "base_cost": 0.5}, {"name": "Nirnroot", "effect": "Damage Health", "base_magnitude": 2, "base_cost": 3.0}, {"name": "Nirnroot", "effect": "Damage Stamina", "base_magnitude": 3, "base_cost": 1.8}, {"name": "Nirnroot", "effect": "Invisibility", "base_magnitude": 0, "base_cost": 100.0}, {"name": "Nirnroot", "effect": "Resist Magic", "base_magnitude": 1, "base_cost": 1.0}, {"name": "Nordic Barnacle", "effect": "Damage Magicka", "base_magnitude": 3, "base_cost": 2.2}, {"name": "Nordic Barnacle", "effect": "Waterbreathing", "base_magnitude": 0, "base_cost": 30.0}, {"name": "Nordic Barnacle", "effect": "Regenerate Health", "base_magnitude": 5, "base_cost": 0.1}, {"name": "Nordic Barnacle", "effect": "Fortify Pickpocket", "base_magnitude": 4, "base_cost": 0.5}, {"name": "Orange Dartwing", "effect": "Restore Stamina", "base_magnitude": 5, "base_cost": 0.6}, {"name": "Orange Dartwing", "effect": "Ravage Magicka", "base_magnitude": 2, "base_cost": 1.0}, {"name": "Orange Dartwing", "effect": "Fortify Pickpocket", "base_magnitude": 4, "base_cost": 0.5}, {"name": "Orange Dartwing", "effect": "Lingering Damage Health", "base_magnitude": 1, "base_cost": 12.0}, {"name": "Pearl", "effect": "Restore Stamina", "base_magnitude": 5, "base_cost": 0.6}, {"name": "Pearl", "effect": "Fortify Block", "base_magnitude": 4, "base_cost": 0.5}, {"name": "Pearl", "effect": "Restore Magicka", "base_magnitude": 5, "base_cost": 0.6}, {"name": "Pearl", "effect": "Resist Shock", "base_magnitude": 3, "base_cost": 0.5}, {"name": "Pine Thrush Egg", "effect": "Restore Stamina", "base_magnitude": 5, "base_cost": 0.6}, {"name": "Pine Thrush Egg", "effect": "Fortify Lockpicking", "base_magnitude": 2, "base_cost": 0.5}, {"name": "Pine Thrush Egg", "effect": "Weakness to Poison", "base_magnitude": 2, "base_cost": 1.0}, {"name": "Pine Thrush Egg", "effect": "Resist Shock", "base_magnitude": 3, "base_cost": 0.5}, {"name": "Powdered Mammoth Tusk", "effect": "Restore Stamina", "base_magnitude": 5, "base_cost": 0.6}, {"name": "Powdered Mammoth Tusk", "effect": "Fortify Sneak", "base_magnitude": 4, "base_cost": 0.5}, {"name": "Powdered Mammoth Tusk", "effect": "Weakness to Fire", "base_magnitude": 3, "base_cost": 0.6}, {"name": "Powdered Mammoth Tusk", "effect": "Fear", "base_magnitude": 1, "base_cost": 5.0}, {"name": "Purple Mountain Flower", "effect": "Restore Stamina", "base_magnitude": 5, "base_cost": 0.6}, {"name": "Purple Mountain Flower", "effect": "Fortify Sneak", "base_magnitude": 4, "base_cost": 0.5}, {"name": "Purple Mountain Flower", "effect": "Lingering Damage Magicka", "base_magnitude": 1, "base_cost": 10.0}, {"name": "Purple Mountain Flower", "effect": "Resist Frost", "base_magnitude": 3, "base_cost": 0.5}, {"name": "Red Mountain Flower", "effect": "Restore Magicka", "base_magnitude": 5, "base_cost": 0.6}, {"name": "Red Mountain Flower", "effect": "Ravage Magicka", "base_magnitude": 2, "base_cost": 1.0}, {"name": "Red Mountain Flower", "effect": "Fortify Magicka", "base_magnitude": 4, "base_cost": 0.3}, {"name": "Red Mountain Flower", "effect": "Damage Health", "base_magnitude": 2, "base_cost": 3.0}, {"name": "River Betty", "effect": "Damage Health", "base_magnitude": 2, "base_cost": 3.0}, {"name": "River Betty", "effect": "Fortify Alteration", "base_magnitude": 4, "base_cost": 0.2}, {"name": "River Betty", "effect": "Slow", "base_magnitude": 50, "base_cost": 1.0}, {"name": "River Betty", "effect": "Fortify Carry Weight", "base_magnitude": 4, "base_cost": 0.15}, {"name": "Rock Warbler Egg", "effect": "Restore Health", "base_magnitude": 5, "base_cost": 0.5}, {"name": "Rock Warbler Egg", "effect": "Fortify One-Handed", "base_magnitude": 4, "base_cost": 0.5}, {"name": "Rock Warbler Egg", "effect": "Damage Stamina", "base_magnitude": 3, "base_cost": 1.8}, {"name": "Rock Warbler Egg", "effect": "Weakness to Magic", "base_magnitude": 2, "base_cost": 1.0}, {"name": "Sabre Cat Tooth", "effect": "Restore Stamina", "base_magnitude": 5, "base_cost": 0.6}, {"name": "Sabre Cat Tooth", "effect": "Fortify Heavy Armor", "base_magnitude": 2, "base_cost": 0.5}, {"name": "Sabre Cat Tooth", "effect": "Fortify Smithing", "base_magnitude": 4, "base_cost": 0.75}, {"name": "Sabre Cat Tooth", "effect": "Weakness to Poison", "base_magnitude": 2, "base_cost": 1.0}, {"name": "Salt Pile", "effect": "Weakness to Magic", "base_magnitude": 2, "base_cost": 1.0}, {"name": "Salt Pile", "effect": "Fortify Restoration", "base_magnitude": 4, "base_cost": 0.5}, {"name": "Salt Pile", "effect": "Slow", "base_magnitude": 50, "base_cost": 1.0}, {"name": "Salt Pile", "effect": "Regenerate Magicka", "base_magnitude": 5, "base_cost": 0.1}, {"name": "Scaly Pholiota", "effect": "Weakness to Magic", "base_magnitude": 2, "base_cost": 1.0}, {"name": "Scaly Pholiota", "effect": "Fortify Illusion", "base_magnitude": 4, "base_cost": 0.4}, {"name": "Scaly Pholiota", "effect": "Regenerate Stamina", "base_magnitude": 5, "base_cost": 0.1}, {"name": "Scaly Pholiota", "effect": "Fortify Carry Weight", "base_magnitude": 4, "base_cost": 0.15}, {"name": "Silverside Perch", "effect": "Restore Stamina", "base_magnitude": 5, "base_cost": 0.6}, {"name": "Silverside Perch", "effect": "Damage Stamina Regen", "base_magnitude": 100, "base_cost": 0.3}, {"name": "Silverside Perch", "effect": "Ravage Health", "base_magnitude": 2, "base_cost": 0.4}, {"name": "Silverside Perch", "effect": "Resist Frost", "base_magnitude": 3, "base_cost": 0.5}, {"name": "Skeever Tail", "effect": "Damage Stamina Regen", "base_magnitude": 100, "base_cost": 0.3}, {"name": "Skeever Tail", "effect": "Ravage Health", "base_magnitude": 2, "base_cost": 0.4}, {"name": "Skeever Tail", "effect": "Damage Health", "base_magnitude": 2, "base_cost": 3.0}, {"name": "Skeever Tail", "effect": "Fortify Light Armor", "base_magnitude": 2, "base_cost": 0.5}, {"name": "Slaughterfish Egg", "effect": "Resist Poison", "base_magnitude": 4, "base_cost": 0.5}, {"name": "Slaughterfish Egg", "effect": "Fortify Pickpocket", "base_magnitude": 4, "base_cost": 0.5}, {"name": "Slaughterfish Egg", "effect": "Lingering Damage Health", "base_magnitude": 1, "base_cost": 12.0}, {"name": "Slaughterfish Egg", "effect": "Fortify Stamina", "base_magnitude": 4, "base_cost": 0.3}, {"name": "Slaughterfish Scales", "effect": "Resist Frost", "base_magnitude": 3, "base_cost": 0.5}, {"name": "Slaughterfish Scales", "effect": "Lingering Damage Health", "base_magnitude": 1, "base_cost": 12.0}, {"name": "Slaughterfish Scales", "effect": "Fortify Heavy Armor", "base_magnitude": 2, "base_cost": 0.5}, {"name": "Slaughterfish Scales", "effect": "Fortify Block", "base_magnitude": 4, "base_cost": 0.5}, {"name": "Small Antlers", "effect": "Weakness to Poison", "base_magnitude": 2, "base_cost": 1.0}, {"name": "Small Antlers", "effect": "Fortify Restoration", "base_magnitude": 4, "base_cost": 0.5}, {"name": "Small Antlers", "effect": "Lingering Damage Stamina", "base_magnitude": 1, "base_cost": 1.8}, {"name": "Small Antlers", "effect": "Damage Health", "base_magnitude": 2, "base_cost": 3.0}, {"name": "Small Pearl", "effect": "Restore Stamina", "base_magnitude": 5, "base_cost": 0.6}, {"name": "Small Pearl", "effect": "Fortify One-Handed", "base_magnitude": 4, "base_cost": 0.5}, {"name": "Small Pearl", "effect": "Fortify Restoration", "base_magnitude": 4, "base_cost": 0.5}, {"name": "Small Pearl", "effect": "Resist Frost", "base_magnitude": 3, "base_cost": 0.5}, {"name": "Snowberries", "effect": "Resist Fire", "base_magnitude": 3, "base_cost": 0.5}, {"name": "Snowberries", "effect": "Fortify Enchanting", "base_magnitude": 1, "base_cost": 0.6}, {"name": "Snowberries", "effect": "Resist Frost", "base_magnitude": 3, "base_cost": 0.5}, {"name": "Snowberries", "effect": "Resist Shock", "base_magnitude": 3, "base_cost": 0.5}, {"name": "Spider Egg", "effect": "Damage Stamina", "base_magnitude": 3, "base_cost": 1.8}, {"name": "Spider Egg", "effect": "Damage Magicka Regen", "base_magnitude": 100, "base_cost": 0.5}, {"name": "Spider Egg", "effect": "Fortify Lockpicking", "base_magnitude": 2, "base_cost": 0.5}, {"name": "Spider Egg", "effect": "Fortify Marksman", "base_magnitude": 4, "base_cost": 0.5}, {"name": "Spriggan Sap", "effect": "Damage Magicka Regen", "base_magnitude": 100, "base_cost": 0.5}, {"name": "Spriggan Sap", "effect": "Fortify Enchanting", "base_magnitude": 1, "base_cost": 0.6}, {"name": "Spriggan Sap", "effect": "Fortify Smithing", "base_magnitude": 4, "base_cost": 0.75}, {"name": "Spriggan Sap", "effect": "Fortify Alteration", "base_magnitude": 4, "base_cost": 0.2}, {"name": "Swamp Fungal Pod", "effect": "Resist Shock", "base_magnitude": 3, "base_cost": 0.5}, {"name": "Swamp Fungal Pod", "effect": "Lingering Damage Magicka", "base_magnitude": 1, "base_cost": 10.0}, {"name": "Swamp Fungal Pod", "effect": "Paralysis", "base_magnitude": 0, "base_cost": 500.0}, {"name": "Swamp Fungal Pod", "effect": "Restore Health", "base_magnitude": 5, "base_cost": 0.5}, {"name": "Taproot", "effect": "Weakness to Magic", "base_magnitude": 2, "base_cost": 1.0}, {"name": "Taproot", "effect": "Fortify Illusion", "base_magnitude": 4, "base_cost": 0.4}, {"name": "Taproot", "effect": "Regenerate Magicka", "base_magnitude": 5, "base_cost": 0.1}, {"name": "Taproot", "effect": "Restore Magicka", "base_magnitude": 5, "base_cost": 0.6}, {"name": "Thistle Branch", "effect": "Resist Frost", "base_magnitude": 3, "base_cost": 0.5}, {"name": "Thistle Branch", "effect": "Ravage Stamina", "base_magnitude": 2, "base_cost": 1.6}, {"name": "Thistle Branch", "effect": "Resist Poison", "base_magnitude": 4, "base_cost": 0.5}, {"name": "Thistle Branch", "effect": "Fortify Heavy Armor", "base_magnitude": 2, "base_cost": 0.5}, {"name": "Torchbug Thorax", "effect": "Restore Stamina", "base_magnitude": 5, "base_cost": 0.6}, {"name": "Torchbug Thorax", "effect": "Lingering Damage Magicka", "base_magnitude": 1, "base_cost": 10.0}, {"name": "Torchbug Thorax", "effect": "Weakness to Magic", "base_magnitude": 2, "base_cost": 1.0}, {"name": "Torchbug Thorax", "effect": "Fortify Stamina", "base_magnitude": 4, "base_cost": 0.3}, {"name": "Troll Fat", "effect": "Resist Poison", "base_magnitude": 4, "base_cost": 0.5}, {"name": "Troll Fat", "effect": "Fortify Two-Handed", "base_magnitude": 4, "base_cost": 0.5}, {"name": "Troll Fat", "effect": "Frenzy", "base_magnitude": 1, "base_cost": 15.0}, {"name": "Troll Fat", "effect": "Damage Health", "base_magnitude": 2, "base_cost": 3.0}, {"name": "Tundra Cotton", "effect": "Resist Magic", "base_magnitude": 1, "base_cost": 1.0}, {"name": "Tundra Cotton", "effect": "Fortify Magicka", "base_magnitude": 4, "base_cost": 0.3}, {"name": "Tundra Cotton", "effect": "Fortify Block", "base_magnitude": 4, "base_cost": 0.5}, {"name": "Tundra Cotton", "effect": "Fortify Barter", "base_magnitude": 1, "base_cost": 2.0}, {"name": "Vampire Dust", "effect": "Invisibility", "base_magnitude": 0, "base_cost": 100.0}, {"name": "Vampire Dust", "effect": "Restore Magicka", "base_magnitude": 5, "base_cost": 0.6}, {"name": "Vampire Dust", "effect": "Regenerate Health", "base_magnitude": 5, "base_cost": 0.1}, {"name": "Vampire Dust", "effect": "Cure Disease", "base_magnitude": 5, "base_cost": 0.5}, {"name": "Void Salts", "effect": "Weakness to Shock", "base_magnitude": 3, "base_cost": 0.7}, {"name": "Void Salts", "effect": "Resist Magic", "base_magnitude": 1, "base_cost": 1.0}, {"name": "Void Salts", "effect": "Damage Health", "base_magnitude": 2, "base_cost": 3.0}, {"name": "Void Salts", "effect": "Fortify Magicka", "base_magnitude": 4, "base_cost": 0.3}, {"name": "Wheat", "effect": "Restore Health", "base_magnitude": 5, "base_cost": 0.5}, {"name": "Wheat", "effect": "Fortify Health", "base_magnitude": 4, "base_cost": 0.35}, {"name": "Wheat", "effect": "Damage Stamina Regen", "base_magnitude": 100, "base_cost": 0.3}, {"name": "Wheat", "effect": "Lingering Damage Magicka", "base_magnitude": 1, "base_cost": 10.0}, {"name": "White Cap", "effect": "Weakness to Frost", "base_magnitude": 3, "base_cost": 0.5}, {"name": "White Cap", "effect": "Fortify Heavy Armor", "base_magnitude": 2, "base_cost": 0.5}, {"name": "White Cap", "effect": "Restore Magicka", "base_magnitude": 5, "base_cost": 0.6}, {"name": "White Cap", "effect": "Ravage Magicka", "base_magnitude": 2, "base_cost": 1.0}, {"name": "Wisp Wrappings", "effect": "Restore Stamina", "base_magnitude": 5, "base_cost": 0.6}, {"name": "Wisp Wrappings", "effect": "Fortify Destruction", "base_magnitude": 5, "base_cost": 0.5}, {"name": "Wisp Wrappings", "effect": "Fortify Carry Weight", "base_magnitude": 4, "base_cost": 0.15}, {"name": "Wisp Wrappings", "effect": "Resist Magic", "base_magnitude": 1, "base_cost": 1.0}, {"name": "Hawk's Egg", "effect": "Resist Magic", "base_magnitude": 1, "base_cost": 1.0}, {"name": "Hawk's Egg", "effect": "Damage Magicka Regen", "base_magnitude": 100, "base_cost": 0.5}, {"name": "Hawk's Egg", "effect": "Waterbreathing", "base_magnitude": 0, "base_cost": 30.0}, {"name": "Hawk's Egg", "effect": "Lingering Damage Stamina", "base_magnitude": 1, "base_cost": 1.8}, {"name": "Salmon Roe", "effect": "Restore Stamina", "base_magnitude": 5, "base_cost": 0.6}, {"name": "Salmon Roe", "effect": "Waterbreathing", "base_magnitude": 0, "base_cost": 30.0}, {"name": "Salmon Roe", "effect": "Fortify Magicka", "base_magnitude": 4, "base_cost": 0.3}, {"name": "Salmon Roe", "effect": "Regenerate Magicka", "base_magnitude": 5, "base_cost": 0.1}, {"name": "Ancestor Moth Wing", "effect": "Damage Stamina", "base_magnitude": 3, "base_cost": 1.8}, {"name": "Ancestor Moth Wing", "effect": "Fortify Conjuration", "base_magnitude": 5, "base_cost": 0.25}, {"name": "Ancestor Moth Wing", "effect": "Damage Magicka Regen", "base_magnitude": 100, "base_cost": 0.5}, {"name": "Ancestor Moth Wing", "effect": "Fortify Enchanting", "base_magnitude": 1, "base_cost": 0.6}, {"name": "Chaurus Hunter Antennae", "effect": "Damage Stamina", "base_magnitude": 3, "base_cost": 1.8}, {"name": "Chaurus Hunter Antennae", "effect": "Fortify Conjuration", "base_magnitude": 5, "base_cost": 0.25}, {"name": "Chaurus Hunter Antennae", "effect": "Damage Magicka Regen", "base_magnitude": 100, "base_cost": 0.5}, {"name": "Chaurus Hunter Antennae", "effect": "Fortify Enchanting", "base_magnitude": 1, "base_cost": 0.6}, {"name": "Gleamblossom", "effect": "Resist Magic", "base_magnitude": 1, "base_cost": 1.0}, {"name": "Gleamblossom", "effect": "Fear", "base_magnitude": 1, "base_cost": 5.0}, {"name": "Gleamblossom", "effect": "Regenerate Health", "base_magnitude": 5, "base_cost": 0.1}, {"name": "Gleamblossom", "effect": "Paralysis", "base_magnitude": 0, "base_cost": 500.0}, {"name": "Poison Bloom", "effect": "Damage Health", "base_magnitude": 2, "base_cost": 3.0}, {"name": "Poison Bloom", "effect": "Slow", "base_magnitude": 50, "base_cost": 1.0}, {"name": "Poison Bloom", "effect": "Fortify Carry Weight", "base_magnitude": 4, "base_cost": 0.15}, {"name": "Poison Bloom", "effect": "Fear", "base_magnitude": 1, "base_cost": 5.0}, {"name": "Yellow Mountain Flower", "effect": "Resist Poison", "base_magnitude": 4, "base_cost": 0.5}, {"name": "Yellow Mountain Flower", "effect": "Fortify Restoration", "base_magnitude": 4, "base_cost": 0.5}, {"name": "Yellow Mountain Flower", "effect": "Fortify Health", "base_magnitude": 4, "base_cost": 0.35}, {"name": "Yellow Mountain Flower", "effect": "Damage Stamina Regen", "base_magnitude": 100, "base_cost": 0.3}, {"name": "Ash Creep Cluster", "effect": "Damage Stamina", "base_magnitude": 3, "base_cost": 1.8}, {"name": "Ash Creep Cluster", "effect": "Invisibility", "base_magnitude": 0, "base_cost": 100.0}, {"name": "Ash Creep Cluster", "effect": "Resist Fire", "base_magnitude": 3, "base_cost": 0.5}, {"name": "Ash Creep Cluster", "effect": "Fortify Destruction", "base_magnitude": 5, "base_cost": 0.5}, {"name": "Ash Hopper Jelly", "effect": "Restore Health", "base_magnitude": 5, "base_cost": 0.5}, {"name": "Ash Hopper Jelly", "effect": "Fortify Light Armor", "base_magnitude": 2, "base_cost": 0.5}, {"name": "Ash Hopper Jelly", "effect": "Resist Shock", "base_magnitude": 3, "base_cost": 0.5}, {"name": "Ash Hopper Jelly", "effect": "Weakness to Frost", "base_magnitude": 3, "base_cost": 0.5}, {"name": "Ashen Grass Pod", "effect": "Resist Fire", "base_magnitude": 3, "base_cost": 0.5}, {"name": "Ashen Grass Pod", "effect": "Weakness to Shock", "base_magnitude": 3, "base_cost": 0.7}, {"name": "Ashen Grass Pod", "effect": "Fortify Lockpicking", "base_magnitude": 2, "base_cost": 0.5}, {"name": "Ashen Grass Pod", "effect": "Fortify Sneak", "base_magnitude": 4, "base_cost": 0.5}, {"name": "Boar Tusk", "effect": "Fortify Stamina", "base_magnitude": 4, "base_cost": 0.3}, {"name": "Boar Tusk", "effect": "Fortify Health", "base_magnitude": 4, "base_cost": 0.35}, {"name": "Boar Tusk", "effect": "Fortify Block", "base_magnitude": 4, "base_cost": 0.5}, {"name": "Boar Tusk", "effect": "Frenzy", "base_magnitude": 1, "base_cost": 15.0}, {"name": "Burnt Spriggan Wood", "effect": "Weakness to Fire", "base_magnitude": 3, "base_cost": 0.6}, {"name": "Burnt Spriggan Wood", "effect": "Fortify Alteration", "base_magnitude": 4, "base_cost": 0.2}, {"name": "Burnt Spriggan Wood", "effect": "Damage Magicka Regen", "base_magnitude": 100, "base_cost": 0.5}, {"name": "Burnt Spriggan Wood", "effect": "Slow", "base_magnitude": 50, "base_cost": 1.0}, {"name": "Emperor Parasol Moss", "effect": "Damage Health", "base_magnitude": 2, "base_cost": 3.0}, {"name": "Emperor Parasol Moss", "effect": "Fortify Magicka", "base_magnitude": 4, "base_cost": 0.3}, {"name": "Emperor Parasol Moss", "effect": "Regenerate Health", "base_magnitude": 5, "base_cost": 0.1}, {"name": "Emperor Parasol Moss", "effect": "Fortify Two-Handed", "base_magnitude": 4, "base_cost": 0.5}, {"name": "Felsaad Tern Feathers", "effect": "Restore Health", "base_magnitude": 5, "base_cost": 0.5}, {"name": "Felsaad Tern Feathers", "effect": "Fortify Light Armor", "base_magnitude": 2, "base_cost": 0.5}, {"name": "Felsaad Tern Feathers", "effect": "Cure Disease", "base_magnitude": 5, "base_cost": 0.5}, {"name": "Felsaad Tern Feathers", "effect": "Resist Magic", "base_magnitude": 1, "base_cost": 1.0}, {"name": "Netch Jelly", "effect": "Paralysis", "base_magnitude": 0, "base_cost": 500.0}, {"name": "Netch Jelly", "effect": "Fortify Carry Weight", "base_magnitude": 4, "base_cost": 0.15}, {"name": "Netch Jelly", "effect": "Restore Stamina", "base_magnitude": 5, "base_cost": 0.6}, {"name": "Netch Jelly", "effect": "Fear", "base_magnitude": 1, "base_cost": 5.0}, {"name": "Scathecraw", "effect": "Ravage Health", "base_magnitude": 2, "base_cost": 0.4}, {"name": "Scathecraw", "effect": "Ravage Stamina", "base_magnitude": 2, "base_cost": 1.6}, {"name": "Scathecraw", "effect": "Ravage Magicka", "base_magnitude": 2, "base_cost": 1.0}, {"name": "Scathecraw", "effect": "Lingering Damage Health", "base_magnitude": 1, "base_cost": 12.0}, {"name": "Spawn Ash", "effect": "Ravage Stamina", "base_magnitude": 2, "base_cost": 1.6}, {"name": "Spawn Ash", "effect": "Resist Fire", "base_magnitude": 3, "base_cost": 0.5}, {"name": "Spawn Ash", "effect": "Fortify Enchanting", "base_magnitude": 1, "base_cost": 0.6}, {"name": "Spawn Ash", "effect": "Ravage Magicka", "base_magnitude": 2, "base_cost": 1.0}, {"name": "Trama Root", "effect": "Weakness to Shock", "base_magnitude": 3, "base_cost": 0.7}, {"name": "Trama Root", "effect": "Fortify Carry Weight", "base_magnitude": 4, "base_cost": 0.15}, {"name": "Trama Root", "effect": "Damage Magicka", "base_magnitude": 3, "base_cost": 2.2}, {"name": "Trama Root", "effect": "Slow", "base_magnitude": 50, "base_cost": 1.0}, {"name": "Alocasia Fruit", "effect": "Regenerate Stamina", "base_magnitude": 5, "base_cost": 0.1}, {"name": "Alocasia Fruit", "effect": "Light", "base_magnitude": 0, "base_cost": 0.5}, {"name": "Alocasia Fruit", "effect": "Ravage Magicka", "base_magnitude": 2, "base_cost": 1.0}, {"name": "Alocasia Fruit", "effect": "Regenerate Health", "base_magnitude": 5, "base_cost": 0.1}, {"name": "Ambrosia", "effect": "Restore Health", "base_magnitude": 5, "base_cost": 0.5}, {"name": "Ambrosia", "effect": "Regenerate Health", "base_magnitude": 5, "base_cost": 0.1}, {"name": "Ambrosia", "effect": "Fortify Health", "base_magnitude": 4, "base_cost": 0.35}, {"name": "Ambrosia", "effect": "Cure Poison", "base_magnitude": 2, "base_cost": 0.2}, {"name": "Angelfish", "effect": "Regenerate Health", "base_magnitude": 5, "base_cost": 0.1}, {"name": "Angelfish", "effect": "Resist Fire", "base_magnitude": 3, "base_cost": 0.5}, {"name": "Angelfish", "effect": "Fortify Marksman", "base_magnitude": 4, "base_cost": 0.5}, {"name": "Angelfish", "effect": "Waterbreathing", "base_magnitude": 0, "base_cost": 30.0}, {"name": "Angler Larvae", "effect": "Lingering Damage Health", "base_magnitude": 1, "base_cost": 12.0}, {"name": "Angler Larvae", "effect": "Regenerate Stamina", "base_magnitude": 5, "base_cost": 0.1}, {"name": "Angler Larvae", "effect": "Waterbreathing", "base_magnitude": 0, "base_cost": 30.0}, {"name": "Angler Larvae", "effect": "Fortify Two-Handed", "base_magnitude": 4, "base_cost": 0.5}, {"name": "Aster Bloom Core", "effect": "Resist Magic", "base_magnitude": 1, "base_cost": 1.0}, {"name": "Aster Bloom Core", "effect": "Fortify Light Armor", "base_magnitude": 2, "base_cost": 0.5}, {"name": "Aster Bloom Core", "effect": "Fortify Block", "base_magnitude": 4, "base_cost": 0.5}, {"name": "Aster Bloom Core", "effect": "Paralysis", "base_magnitude": 0, "base_cost": 500.0}, {"name": "Bittergreen Petals", "effect": "Lingering Damage Stamina", "base_magnitude": 1, "base_cost": 1.8}, {"name": "Bittergreen Petals", "effect": "Invisibility", "base_magnitude": 0, "base_cost": 100.0}, {"name": "Bittergreen Petals", "effect": "Cure Poison", "base_magnitude": 2, "base_cost": 0.2}, {"name": "Bittergreen Petals", "effect": "Damage Magicka", "base_magnitude": 3, "base_cost": 2.2}, {"name": "Blind Watcher's Eye", "effect": "Light", "base_magnitude": 0, "base_cost": 0.5}, {"name": "Blind Watcher's Eye", "effect": "Fortify Magicka", "base_magnitude": 4, "base_cost": 0.3}, {"name": "Blind Watcher's Eye", "effect": "Fortify Alteration", "base_magnitude": 4, "base_cost": 0.2}, {"name": "Blind Watcher's Eye", "effect": "Spell Absorption", "base_magnitude": 50, "base_cost": 0.1}, {"name": "Bliss Bug Thorax", "effect": "Weakness to Fire", "base_magnitude": 3, "base_cost": 0.6}, {"name": "Bliss Bug Thorax", "effect": "Resist Fire", "base_magnitude": 3, "base_cost": 0.5}, {"name": "Bliss Bug Thorax", "effect": "Fortify Heavy Armor", "base_magnitude": 2, "base_cost": 0.5}, {"name": "Bliss Bug Thorax", "effect": "Fortify Illusion", "base_magnitude": 4, "base_cost": 0.4}, {"name": "Blister Pod Cap", "effect": "Restore Magicka", "base_magnitude": 5, "base_cost": 0.6}, {"name": "Blister Pod Cap", "effect": "Fortify Magicka", "base_magnitude": 4, "base_cost": 0.3}, {"name": "Blister Pod Cap", "effect": "Night Eye", "base_magnitude": 0, "base_cost": 0.75}, {"name": "Blister Pod Cap", "effect": "Invisibility", "base_magnitude": 0, "base_cost": 100.0}, {"name": "Bloodgrass", "effect": "Invisibility", "base_magnitude": 0, "base_cost": 100.0}, {"name": "Bloodgrass", "effect": "Resist Poison", "base_magnitude": 4, "base_cost": 0.5}, {"name": "Bloodgrass", "effect": "Slow", "base_magnitude": 50, "base_cost": 1.0}, {"name": "Bloodgrass", "effect": "Fortify Health", "base_magnitude": 4, "base_cost": 0.35}, {"name": "Bog Beacon", "effect": "Restore Magicka", "base_magnitude": 5, "base_cost": 0.6}, {"name": "Bog Beacon", "effect": "Fortify Heavy Armor", "base_magnitude": 2, "base_cost": 0.5}, {"name": "Bog Beacon", "effect": "Fear", "base_magnitude": 1, "base_cost": 5.0}, {"name": "Bog Beacon", "effect": "Damage Stamina", "base_magnitude": 3, "base_cost": 1.8}, {"name": "Bungler's Bane", "effect": "Slow", "base_magnitude": 50, "base_cost": 1.0}, {"name": "Bungler's Bane", "effect": "Ravage Stamina", "base_magnitude": 2, "base_cost": 1.6}, {"name": "Bungler's Bane", "effect": "Damage Stamina Regen", "base_magnitude": 100, "base_cost": 0.3}, {"name": "Bungler's Bane", "effect": "Resist Magic", "base_magnitude": 1, "base_cost": 1.0}, {"name": "Chokeberry", "effect": "Damage Health", "base_magnitude": 2, "base_cost": 3.0}, {"name": "Chokeberry", "effect": "Ravage Health", "base_magnitude": 2, "base_cost": 0.4}, {"name": "Chokeberry", "effect": "Lingering Damage Health", "base_magnitude": 1, "base_cost": 12.0}, {"name": "Chokeberry", "effect": "Weakness to Poison", "base_magnitude": 2, "base_cost": 1.0}, {"name": "Chokeweed", "effect": "Weakness to Frost", "base_magnitude": 3, "base_cost": 0.5}, {"name": "Chokeweed", "effect": "Restore Stamina", "base_magnitude": 5, "base_cost": 0.6}, {"name": "Chokeweed", "effect": "Cure Disease", "base_magnitude": 5, "base_cost": 0.5}, {"name": "Chokeweed", "effect": "Damage Magicka", "base_magnitude": 3, "base_cost": 2.2}, {"name": "Coda Flower", "effect": "Damage Health", "base_magnitude": 2, "base_cost": 3.0}, {"name": "Coda Flower", "effect": "Lingering Damage Stamina", "base_magnitude": 1, "base_cost": 1.8}, {"name": "Coda Flower", "effect": "Ravage Magicka", "base_magnitude": 2, "base_cost": 1.0}, {"name": "Coda Flower", "effect": "Fortify Carry Weight", "base_magnitude": 4, "base_cost": 0.15}, {"name": "Comberry", "effect": "Damage Stamina", "base_magnitude": 3, "base_cost": 1.8}, {"name": "Comberry", "effect": "Spell Absorption", "base_magnitude": 50, "base_cost": 0.1}, {"name": "Comberry", "effect": "Restore Magicka", "base_magnitude": 5, "base_cost": 0.6}, {"name": "Comberry", "effect": "Fortify Destruction", "base_magnitude": 5, "base_cost": 0.5}, {"name": "Congealed Putrescence", "effect": "Ravage Health", "base_magnitude": 2, "base_cost": 0.4}, {"name": "Congealed Putrescence", "effect": "Restore Magicka", "base_magnitude": 5, "base_cost": 0.6}, {"name": "Congealed Putrescence", "effect": "Weakness to Fire", "base_magnitude": 3, "base_cost": 0.6}, {"name": "Congealed Putrescence", "effect": "Fortify Conjuration", "base_magnitude": 5, "base_cost": 0.25}, {"name": "Corkbulb Root", "effect": "Paralysis", "base_magnitude": 0, "base_cost": 500.0}, {"name": "Corkbulb Root", "effect": "Restore Health", "base_magnitude": 5, "base_cost": 0.5}, {"name": "Corkbulb Root", "effect": "Resist Shock", "base_magnitude": 3, "base_cost": 0.5}, {"name": "Corkbulb Root", "effect": "Fortify Marksman", "base_magnitude": 4, "base_cost": 0.5}, {"name": "Corrupted Human Heart", "effect": "Damage Health", "base_magnitude": 2, "base_cost": 3.0}, {"name": "Corrupted Human Heart", "effect": "Damage Magicka", "base_magnitude": 3, "base_cost": 2.2}, {"name": "Corrupted Human Heart", "effect": "Damage Magicka Regen", "base_magnitude": 100, "base_cost": 0.5}, {"name": "Corrupted Human Heart", "effect": "Frenzy", "base_magnitude": 1, "base_cost": 15.0}, {"name": "Daedra Silk", "effect": "Lingering Damage Stamina", "base_magnitude": 1, "base_cost": 1.8}, {"name": "Daedra Silk", "effect": "Paralysis", "base_magnitude": 0, "base_cost": 500.0}, {"name": "Daedra Silk", "effect": "Night Eye", "base_magnitude": 0, "base_cost": 0.75}, {"name": "Daedra Silk", "effect": "Invisibility", "base_magnitude": 0, "base_cost": 100.0}, {"name": "Daedra Venin", "effect": "Ravage Health", "base_magnitude": 2, "base_cost": 0.4}, {"name": "Daedra Venin", "effect": "Paralysis", "base_magnitude": 0, "base_cost": 500.0}, {"name": "Daedra Venin", "effect": "Fortify Destruction", "base_magnitude": 5, "base_cost": 0.5}, {"name": "Daedra Venin", "effect": "Spell Absorption", "base_magnitude": 50, "base_cost": 0.1}, {"name": "Daedroth Teeth", "effect": "Resist Frost", "base_magnitude": 3, "base_cost": 0.5}, {"name": "Daedroth Teeth", "effect": "Light", "base_magnitude": 0, "base_cost": 0.5}, {"name": "Daedroth Teeth", "effect": "Damage Magicka Regen", "base_magnitude": 100, "base_cost": 0.5}, {"name": "Daedroth Teeth", "effect": "Regenerate Stamina", "base_magnitude": 5, "base_cost": 0.1}, {"name": "Dreugh Wax", "effect": "Weakness to Magic", "base_magnitude": 2, "base_cost": 1.0}, {"name": "Dreugh Wax", "effect": "Frenzy", "base_magnitude": 1, "base_cost": 15.0}, {"name": "Dreugh Wax", "effect": "Fortify Enchanting", "base_magnitude": 1, "base_cost": 0.6}, {"name": "Dreugh Wax", "effect": "Fortify Smithing", "base_magnitude": 4, "base_cost": 0.75}, {"name": "Elytra Ichor", "effect": "Restore Magicka", "base_magnitude": 5, "base_cost": 0.6}, {"name": "Elytra Ichor", "effect": "Invisibility", "base_magnitude": 0, "base_cost": 100.0}, {"name": "Elytra Ichor", "effect": "Slow", "base_magnitude": 50, "base_cost": 1.0}, {"name": "Elytra Ichor", "effect": "Fear", "base_magnitude": 1, "base_cost": 5.0}, {"name": "Fire Petal", "effect": "Damage Health", "base_magnitude": 2, "base_cost": 3.0}, {"name": "Fire Petal", "effect": "Resist Fire", "base_magnitude": 3, "base_cost": 0.5}, {"name": "Fire Petal", "effect": "Spell Absorption", "base_magnitude": 50, "base_cost": 0.1}, {"name": "Fire Petal", "effect": "Paralysis", "base_magnitude": 0, "base_cost": 500.0}, {"name": "Flame Stalk", "effect": "Restore Health", "base_magnitude": 5, "base_cost": 0.5}, {"name": "Flame Stalk", "effect": "Resist Frost", "base_magnitude": 3, "base_cost": 0.5}, {"name": "Flame Stalk", "effect": "Weakness to Fire", "base_magnitude": 3, "base_cost": 0.6}, {"name": "Flame Stalk", "effect": "Invisibility", "base_magnitude": 0, "base_cost": 100.0}, {"name": "Fungus Stalk", "effect": "Restore Magicka", "base_magnitude": 5, "base_cost": 0.6}, {"name": "Fungus Stalk", "effect": "Fortify Health", "base_magnitude": 4, "base_cost": 0.35}, {"name": "Fungus Stalk", "effect": "Fortify Stamina", "base_magnitude": 4, "base_cost": 0.3}, {"name": "Fungus Stalk", "effect": "Waterbreathing", "base_magnitude": 0, "base_cost": 30.0}, {"name": "Glassfish", "effect": "Restore Magicka", "base_magnitude": 5, "base_cost": 0.6}, {"name": "Glassfish", "effect": "Invisibility", "base_magnitude": 0, "base_cost": 100.0}, {"name": "Glassfish", "effect": "Fortify Illusion", "base_magnitude": 4, "base_cost": 0.4}, {"name": "Glassfish", "effect": "Fortify Persuasion", "base_magnitude": null, "base_cost": null}, {"name": "Gnarl Bark", "effect": "Damage Health", "base_magnitude": 2, "base_cost": 3.0}, {"name": "Gnarl Bark", "effect": "Regenerate Health", "base_magnitude": 5, "base_cost": 0.1}, {"name": "Gnarl Bark", "effect": "Fortify Heavy Armor", "base_magnitude": 2, "base_cost": 0.5}, {"name": "Gnarl Bark", "effect": "Resist Fire", "base_magnitude": 3, "base_cost": 0.5}, {"name": "Gold Kanet", "effect": "Paralysis", "base_magnitude": 0, "base_cost": 500.0}, {"name": "Gold Kanet", "effect": "Ravage Health", "base_magnitude": 2, "base_cost": 0.4}, {"name": "Gold Kanet", "effect": "Weakness to Frost", "base_magnitude": 3, "base_cost": 0.5}, {"name": "Gold Kanet", "effect": "Fortify Smithing", "base_magnitude": 4, "base_cost": 0.75}, {"name": "Goldfish", "effect": "Restore Stamina", "base_magnitude": 5, "base_cost": 0.6}, {"name": "Goldfish", "effect": "Fortify Heavy Armor", "base_magnitude": 2, "base_cost": 0.5}, {"name": "Goldfish", "effect": "Waterbreathing", "base_magnitude": 0, "base_cost": 30.0}, {"name": "Goldfish", "effect": "Resist Frost", "base_magnitude": 3, "base_cost": 0.5}, {"name": "Green Butterfly Wing", "effect": "Restore Magicka", "base_magnitude": 5, "base_cost": 0.6}, {"name": "Green Butterfly Wing", "effect": "Fear", "base_magnitude": 1, "base_cost": 5.0}, {"name": "Green Butterfly Wing", "effect": "Slow", "base_magnitude": 50, "base_cost": 1.0}, {"name": "Green Butterfly Wing", "effect": "Invisibility", "base_magnitude": 0, "base_cost": 100.0}, {"name": "Hackle-Lo Leaf", "effect": "Restore Stamina", "base_magnitude": 5, "base_cost": 0.6}, {"name": "Hackle-Lo Leaf", "effect": "Paralysis", "base_magnitude": 0, "base_cost": 500.0}, {"name": "Hackle-Lo Leaf", "effect": "Waterbreathing", "base_magnitude": 0, "base_cost": 30.0}, {"name": "Hackle-Lo Leaf", "effect": "Fortify Restoration", "base_magnitude": 4, "base_cost": 0.5}, {"name": "Harrada", "effect": "Damage Health", "base_magnitude": 2, "base_cost": 3.0}, {"name": "Harrada", "effect": "Damage Magicka", "base_magnitude": 3, "base_cost": 2.2}, {"name": "Harrada", "effect": "Paralysis", "base_magnitude": 0, "base_cost": 500.0}, {"name": "Harrada", "effect": "Damage Magicka Regen", "base_magnitude": 100, "base_cost": 0.5}, {"name": "Healing Salts", "effect": "Weakness to Magic", "base_magnitude": 2, "base_cost": 1.0}, {"name": "Healing Salts", "effect": "Fortify Restoration", "base_magnitude": 4, "base_cost": 0.5}, {"name": "Healing Salts", "effect": "Slow", "base_magnitude": 50, "base_cost": 1.0}, {"name": "Healing Salts", "effect": "Regenerate Magicka", "base_magnitude": 5, "base_cost": 0.1}, {"name": "Heart of Order", "effect": "Restore Health", "base_magnitude": 5, "base_cost": 0.5}, {"name": "Heart of Order", "effect": "Fortify Health", "base_magnitude": 4, "base_cost": 0.35}, {"name": "Heart of Order", "effect": "Fortify One-Handed", "base_magnitude": 4, "base_cost": 0.5}, {"name": "Heart of Order", "effect": "Fortify Two-Handed", "base_magnitude": 4, "base_cost": 0.5}, {"name": "Hunger Tongue", "effect": "Weakness to Fire", "base_magnitude": 3, "base_cost": 0.6}, {"name": "Hunger Tongue", "effect": "Cure Disease", "base_magnitude": 5, "base_cost": 0.5}, {"name": "Hunger Tongue", "effect": "Cure Poison", "base_magnitude": 2, "base_cost": 0.2}, {"name": "Hunger Tongue", "effect": "Fortify Magicka", "base_magnitude": 4, "base_cost": 0.3}, {"name": "Hydnum Azure Giant Spore", "effect": "Resist Frost", "base_magnitude": 3, "base_cost": 0.5}, {"name": "Hydnum Azure Giant Spore", "effect": "Fortify Health", "base_magnitude": 4, "base_cost": 0.35}, {"name": "Hydnum Azure Giant Spore", "effect": "Regenerate Health", "base_magnitude": 5, "base_cost": 0.1}, {"name": "Hydnum Azure Giant Spore", "effect": "Light", "base_magnitude": 0, "base_cost": 0.5}, {"name": "Hypha Facia", "effect": "Weakness to Poison", "base_magnitude": 2, "base_cost": 1.0}, {"name": "Hypha Facia", "effect": "Frenzy", "base_magnitude": 1, "base_cost": 15.0}, {"name": "Hypha Facia", "effect": "Ravage Stamina", "base_magnitude": 2, "base_cost": 1.6}, {"name": "Hypha Facia", "effect": "Resist Magic", "base_magnitude": 1, "base_cost": 1.0}, {"name": "Imp Gall", "effect": "Damage Health", "base_magnitude": 2, "base_cost": 3.0}, {"name": "Imp Gall", "effect": "Weakness to Fire", "base_magnitude": 3, "base_cost": 0.6}, {"name": "Imp Gall", "effect": "Fortify Barter", "base_magnitude": 1, "base_cost": 2.0}, {"name": "Imp Gall", "effect": "Cure Poison", "base_magnitude": 2, "base_cost": 0.2}, {"name": "Ironwood Fruit", "effect": "Restore Health", "base_magnitude": 5, "base_cost": 0.5}, {"name": "Ironwood Fruit", "effect": "Resist Fire", "base_magnitude": 3, "base_cost": 0.5}, {"name": "Ironwood Fruit", "effect": "Damage Stamina", "base_magnitude": 3, "base_cost": 1.8}, {"name": "Ironwood Fruit", "effect": "Restore Magicka", "base_magnitude": 5, "base_cost": 0.6}, {"name": "Juvenile Mudcrab", "effect": "Regenerate Stamina", "base_magnitude": 5, "base_cost": 0.1}, {"name": "Juvenile Mudcrab", "effect": "Fortify Carry Weight", "base_magnitude": 4, "base_cost": 0.15}, {"name": "Juvenile Mudcrab", "effect": "Cure Disease", "base_magnitude": 5, "base_cost": 0.5}, {"name": "Juvenile Mudcrab", "effect": "Fortify Two-Handed", "base_magnitude": 4, "base_cost": 0.5}, {"name": "Kagouti Hide", "effect": "Lingering Damage Stamina", "base_magnitude": 1, "base_cost": 1.8}, {"name": "Kagouti Hide", "effect": "Night Eye", "base_magnitude": 0, "base_cost": 0.75}, {"name": "Kagouti Hide", "effect": "Fortify Carry Weight", "base_magnitude": 4, "base_cost": 0.15}, {"name": "Kagouti Hide", "effect": "Resist Shock", "base_magnitude": 3, "base_cost": 0.5}, {"name": "Kresh Fiber", "effect": "Weakness to Magic", "base_magnitude": 2, "base_cost": 1.0}, {"name": "Kresh Fiber", "effect": "Slow", "base_magnitude": 50, "base_cost": 1.0}, {"name": "Kresh Fiber", "effect": "Fortify Sneak", "base_magnitude": 4, "base_cost": 0.5}, {"name": "Kresh Fiber", "effect": "Fortify Pickpocket", "base_magnitude": 4, "base_cost": 0.5}, {"name": "Lichor", "effect": "Restore Magicka", "base_magnitude": 5, "base_cost": 0.6}, {"name": "Lichor", "effect": "Regenerate Magicka", "base_magnitude": 5, "base_cost": 0.1}, {"name": "Lichor", "effect": "Fortify Magicka", "base_magnitude": 4, "base_cost": 0.3}, {"name": "Lichor", "effect": "Spell Absorption", "base_magnitude": 50, "base_cost": 0.1}, {"name": "Luminous Russula", "effect": "Lingering Damage Stamina", "base_magnitude": 1, "base_cost": 1.8}, {"name": "Luminous Russula", "effect": "Lingering Damage Health", "base_magnitude": 1, "base_cost": 12.0}, {"name": "Luminous Russula", "effect": "Waterbreathing", "base_magnitude": 0, "base_cost": 30.0}, {"name": "Luminous Russula", "effect": "Fear", "base_magnitude": 1, "base_cost": 5.0}, {"name": "Lyretail Anthias", "effect": "Restore Magicka", "base_magnitude": 5, "base_cost": 0.6}, {"name": "Lyretail Anthias", "effect": "Fortify Alteration", "base_magnitude": 4, "base_cost": 0.2}, {"name": "Lyretail Anthias", "effect": "Fortify Conjuration", "base_magnitude": 5, "base_cost": 0.25}, {"name": "Lyretail Anthias", "effect": "Fortify Carry Weight", "base_magnitude": 4, "base_cost": 0.15}, {"name": "Marshmerrow", "effect": "Restore Health", "base_magnitude": 5, "base_cost": 0.5}, {"name": "Marshmerrow", "effect": "Fortify Carry Weight", "base_magnitude": 4, "base_cost": 0.15}, {"name": "Marshmerrow", "effect": "Weakness to Magic", "base_magnitude": 2, "base_cost": 1.0}, {"name": "Marshmerrow", "effect": "Damage Stamina", "base_magnitude": 3, "base_cost": 1.8}, {"name": "Minotaur Horn", "effect": "Resist Poison", "base_magnitude": 4, "base_cost": 0.5}, {"name": "Minotaur Horn", "effect": "Damage Magicka Regen", "base_magnitude": 100, "base_cost": 0.5}, {"name": "Minotaur Horn", "effect": "Regenerate Health", "base_magnitude": 5, "base_cost": 0.1}, {"name": "Minotaur Horn", "effect": "Regenerate Magicka", "base_magnitude": 5, "base_cost": 0.1}, {"name": "Mort Flesh", "effect": "Damage Health", "base_magnitude": 2, "base_cost": 3.0}, {"name": "Mort Flesh", "effect": "Damage Magicka", "base_magnitude": 3, "base_cost": 2.2}, {"name": "Mort Flesh", "effect": "Damage Magicka Regen", "base_magnitude": 100, "base_cost": 0.5}, {"name": "Mort Flesh", "effect": "Frenzy", "base_magnitude": 1, "base_cost": 15.0}, {"name": "Ogre's Teeth", "effect": "Weakness to Shock", "base_magnitude": 3, "base_cost": 0.7}, {"name": "Ogre's Teeth", "effect": "Resist Poison", "base_magnitude": 4, "base_cost": 0.5}, {"name": "Ogre's Teeth", "effect": "Lingering Damage Magicka", "base_magnitude": 1, "base_cost": 10.0}, {"name": "Ogre's Teeth", "effect": "Regenerate Health", "base_magnitude": 5, "base_cost": 0.1}, {"name": "Pearlfish", "effect": "Restore Stamina", "base_magnitude": 5, "base_cost": 0.6}, {"name": "Pearlfish", "effect": "Resist Frost", "base_magnitude": 3, "base_cost": 0.5}, {"name": "Pearlfish", "effect": "Fortify Smithing", "base_magnitude": 4, "base_cost": 0.75}, {"name": "Pearlfish", "effect": "Fortify One-Handed", "base_magnitude": 4, "base_cost": 0.5}, {"name": "Purple Butterfly Wing", "effect": "Regenerate Health", "base_magnitude": 5, "base_cost": 0.1}, {"name": "Purple Butterfly Wing", "effect": "Regenerate Magicka", "base_magnitude": 5, "base_cost": 0.1}, {"name": "Purple Butterfly Wing", "effect": "Regenerate Stamina", "base_magnitude": 5, "base_cost": 0.1}, {"name": "Purple Butterfly Wing", "effect": "Paralysis", "base_magnitude": 0, "base_cost": 500.0}, {"name": "Pygmy Sunfish", "effect": "Restore Stamina", "base_magnitude": 5, "base_cost": 0.6}, {"name": "Pygmy Sunfish", "effect": "Lingering Damage Magicka", "base_magnitude": 1, "base_cost": 10.0}, {"name": "Pygmy Sunfish", "effect": "Damage Magicka Regen", "base_magnitude": 100, "base_cost": 0.5}, {"name": "Pygmy Sunfish", "effect": "Fortify Restoration", "base_magnitude": 4, "base_cost": 0.5}, {"name": "Red Kelp Gas Bladder", "effect": "Regenerate Stamina", "base_magnitude": 5, "base_cost": 0.1}, {"name": "Red Kelp Gas Bladder", "effect": "Waterbreathing", "base_magnitude": 0, "base_cost": 30.0}, {"name": "Red Kelp Gas Bladder", "effect": "Cure Disease", "base_magnitude": 5, "base_cost": 0.5}, {"name": "Red Kelp Gas Bladder", "effect": "Fortify Magicka", "base_magnitude": 4, "base_cost": 0.3}, {"name": "Redwort Flower", "effect": "Resist Frost", "base_magnitude": 3, "base_cost": 0.5}, {"name": "Redwort Flower", "effect": "Cure Poison", "base_magnitude": 2, "base_cost": 0.2}, {"name": "Redwort Flower", "effect": "Damage Health", "base_magnitude": 2, "base_cost": 3.0}, {"name": "Redwort Flower", "effect": "Invisibility", "base_magnitude": 0, "base_cost": 100.0}, {"name": "Roobrush", "effect": "Weakness to Magic", "base_magnitude": 2, "base_cost": 1.0}, {"name": "Roobrush", "effect": "Fortify Sneak", "base_magnitude": 4, "base_cost": 0.5}, {"name": "Roobrush", "effect": "Lingering Damage Health", "base_magnitude": 1, "base_cost": 12.0}, {"name": "Roobrush", "effect": "Cure Poison", "base_magnitude": 2, "base_cost": 0.2}, {"name": "Rot Scale", "effect": "Slow", "base_magnitude": 50, "base_cost": 1.0}, {"name": "Rot Scale", "effect": "Lingering Damage Health", "base_magnitude": 1, "base_cost": 12.0}, {"name": "Rot Scale", "effect": "Fear", "base_magnitude": 1, "base_cost": 5.0}, {"name": "Rot Scale", "effect": "Paralysis", "base_magnitude": 0, "base_cost": 500.0}, {"name": "Saltrice", "effect": "Restore Stamina", "base_magnitude": 5, "base_cost": 0.6}, {"name": "Saltrice", "effect": "Fortify Magicka", "base_magnitude": 4, "base_cost": 0.3}, {"name": "Saltrice", "effect": "Damage Stamina Regen", "base_magnitude": 100, "base_cost": 0.3}, {"name": "Saltrice", "effect": "Restore Health", "base_magnitude": 5, "base_cost": 0.5}, {"name": "Scalon Fin", "effect": "Waterbreathing", "base_magnitude": 0, "base_cost": 30.0}, {"name": "Scalon Fin", "effect": "Damage Health", "base_magnitude": 2, "base_cost": 3.0}, {"name": "Scalon Fin", "effect": "Lingering Damage Magicka", "base_magnitude": 1, "base_cost": 10.0}, {"name": "Scalon Fin", "effect": "Damage Magicka Regen", "base_magnitude": 100, "base_cost": 0.5}, {"name": "Screaming Maw", "effect": "Regenerate Magicka", "base_magnitude": 5, "base_cost": 0.1}, {"name": "Screaming Maw", "effect": "Fortify Alteration", "base_magnitude": 4, "base_cost": 0.2}, {"name": "Screaming Maw", "effect": "Invisibility", "base_magnitude": 0, "base_cost": 100.0}, {"name": "Screaming Maw", "effect": "Regenerate Health", "base_magnitude": 5, "base_cost": 0.1}, {"name": "Scrib Jelly", "effect": "Regenerate Magicka", "base_magnitude": 5, "base_cost": 0.1}, {"name": "Scrib Jelly", "effect": "Cure Poison", "base_magnitude": 2, "base_cost": 0.2}, {"name": "Scrib Jelly", "effect": "Cure Disease", "base_magnitude": 5, "base_cost": 0.5}, {"name": "Scrib Jelly", "effect": "Regenerate Stamina", "base_magnitude": 5, "base_cost": 0.1}, {"name": "Scrib Jerky", "effect": "Restore Stamina", "base_magnitude": 5, "base_cost": 0.6}, {"name": "Scrib Jerky", "effect": "Fortify Stamina", "base_magnitude": 4, "base_cost": 0.3}, {"name": "Scrib Jerky", "effect": "Paralysis", "base_magnitude": 0, "base_cost": 500.0}, {"name": "Scrib Jerky", "effect": "Waterbreathing", "base_magnitude": 0, "base_cost": 30.0}, {"name": "Simon Rodayne's Heart", "effect": "Damage Health", "base_magnitude": 2, "base_cost": 3.0}, {"name": "Simon Rodayne's Heart", "effect": "Damage Magicka", "base_magnitude": 3, "base_cost": 2.2}, {"name": "Simon Rodayne's Heart", "effect": "Damage Magicka Regen", "base_magnitude": 100, "base_cost": 0.5}, {"name": "Simon Rodayne's Heart", "effect": "Frenzy", "base_magnitude": 1, "base_cost": 15.0}, {"name": "Sload Soap", "effect": "Resist Fire", "base_magnitude": 3, "base_cost": 0.5}, {"name": "Sload Soap", "effect": "Fear", "base_magnitude": 1, "base_cost": 5.0}, {"name": "Sload Soap", "effect": "Fortify Conjuration", "base_magnitude": 5, "base_cost": 0.25}, {"name": "Sload Soap", "effect": "Fortify Alteration", "base_magnitude": 4, "base_cost": 0.2}, {"name": "Spadefish", "effect": "Restore Health", "base_magnitude": 5, "base_cost": 0.5}, {"name": "Spadefish", "effect": "Fortify Lockpicking", "base_magnitude": 2, "base_cost": 0.5}, {"name": "Spadefish", "effect": "Fortify Pickpocket", "base_magnitude": 4, "base_cost": 0.5}, {"name": "Spadefish", "effect": "Cure Disease", "base_magnitude": 5, "base_cost": 0.5}, {"name": "Spiddal Stick", "effect": "Damage Health", "base_magnitude": 2, "base_cost": 3.0}, {"name": "Spiddal Stick", "effect": "Damage Magicka", "base_magnitude": 3, "base_cost": 2.2}, {"name": "Spiddal Stick", "effect": "Weakness to Fire", "base_magnitude": 3, "base_cost": 0.6}, {"name": "Spiddal Stick", "effect": "Restore Stamina", "base_magnitude": 5, "base_cost": 0.6}, {"name": "Steel-Blue Entoloma", "effect": "Restore Magicka", "base_magnitude": 5, "base_cost": 0.6}, {"name": "Steel-Blue Entoloma", "effect": "Fortify Destruction", "base_magnitude": 5, "base_cost": 0.5}, {"name": "Steel-Blue Entoloma", "effect": "Resist Frost", "base_magnitude": 3, "base_cost": 0.5}, {"name": "Steel-Blue Entoloma", "effect": "Fortify Carry Weight", "base_magnitude": 4, "base_cost": 0.15}, {"name": "Stoneflower Petals", "effect": "Weakness to Shock", "base_magnitude": 3, "base_cost": 0.7}, {"name": "Stoneflower Petals", "effect": "Fortify One-Handed", "base_magnitude": 4, "base_cost": 0.5}, {"name": "Stoneflower Petals", "effect": "Fortify Magicka", "base_magnitude": 4, "base_cost": 0.3}, {"name": "Stoneflower Petals", "effect": "Fortify Enchanting", "base_magnitude": 1, "base_cost": 0.6}, {"name": "Thorn Hook", "effect": "Lingering Damage Health", "base_magnitude": 1, "base_cost": 12.0}, {"name": "Thorn Hook", "effect": "Paralysis", "base_magnitude": 0, "base_cost": 500.0}, {"name": "Thorn Hook", "effect": "Regenerate Magicka", "base_magnitude": 5, "base_cost": 0.1}, {"name": "Thorn Hook", "effect": "Regenerate Health", "base_magnitude": 5, "base_cost": 0.1}, {"name": "Void Essence", "effect": "Restore Health", "base_magnitude": 5, "base_cost": 0.5}, {"name": "Void Essence", "effect": "Fortify Health", "base_magnitude": 4, "base_cost": 0.35}, {"name": "Void Essence", "effect": "Fortify Stamina", "base_magnitude": 4, "base_cost": 0.3}, {"name": "Void Essence", "effect": "Regenerate Health", "base_magnitude": 5, "base_cost": 0.1}, {"name": "Watcher's Eye", "effect": "Night Eye", "base_magnitude": 0, "base_cost": 0.75}, {"name": "Watcher's Eye", "effect": "Fortify Magicka", "base_magnitude": 4, "base_cost": 0.3}, {"name": "Watcher's Eye", "effect": "Fortify Illusion", "base_magnitude": 4, "base_cost": 0.4}, {"name": "Watcher's Eye", "effect": "Spell Absorption", "base_magnitude": 50, "base_cost": 0.1}, {"name": "Wild Grass Pod", "effect": "Resist Poison", "base_magnitude": 4, "base_cost": 0.5}, {"name": "Wild Grass Pod", "effect": "Ravage Magicka", "base_magnitude": 2, "base_cost": 1.0}, {"name": "Wild Grass Pod", "effect": "Fortify Alteration", "base_magnitude": 4, "base_cost": 0.2}, {"name": "Wild Grass Pod", "effect": "Restore Magicka", "base_magnitude": 5, "base_cost": 0.6}, {"name": "Wisp Stalk Caps", "effect": "Damage Health", "base_magnitude": 2, "base_cost": 3.0}, {"name": "Wisp Stalk Caps", "effect": "Weakness to Poison", "base_magnitude": 2, "base_cost": 1.0}, {"name": "Wisp Stalk Caps", "effect": "Frenzy", "base_magnitude": 1, "base_cost": 15.0}, {"name": "Wisp Stalk Caps", "effect": "Regenerate Stamina", "base_magnitude": 5, "base_cost": 0.1}, {"name": "Withering Moon", "effect": "Restore Magicka", "base_magnitude": 5, "base_cost": 0.6}, {"name": "Withering Moon", "effect": "Spell Absorption", "base_magnitude": 50, "base_cost": 0.1}, {"name": "Withering Moon", "effect": "Fortify Light Armor", "base_magnitude": 2, "base_cost": 0.5}, {"name": "Withering Moon", "effect": "Cure Disease", "base_magnitude": 5, "base_cost": 0.5}, {"name": "Worm's Head Cap", "effect": "Fortify Lockpicking", "base_magnitude": 2, "base_cost": 0.5}, {"name": "Worm's Head Cap", "effect": "Night Eye", "base_magnitude": 0, "base_cost": 0.75}, {"name": "Worm's Head Cap", "effect": "Fortify Carry Weight", "base_magnitude": 4, "base_cost": 0.15}, {"name": "Worm's Head Cap", "effect": "Slow", "base_magnitude": 50, "base_cost": 1.0}]